Workbook

Sheet overview
A1: Job Search Overview
A2: Last exported | B2: 46202.707
A4: Use Status to track each role. Set Status to applied when you apply, then add the date and details in Notes.
A6: Status | B6: Count
A7: new | B7: =COUNTIF(jobs!$B:$B,A7)
A8: applied | B8: =COUNTIF(jobs!$B:$B,A8)
A9: interview | B9: =COUNTIF(jobs!$B:$B,A9)
A10: offer | B10: =COUNTIF(jobs!$B:$B,A10)
A11: rejected | B11: =COUNTIF(jobs!$B:$B,A11)
A12: ignore | B12: =COUNTIF(jobs!$B:$B,A12)
A13: archive | B13: =COUNTIF(jobs!$B:$B,A13)
A14: closed | B14: =COUNTIF(jobs!$B:$B,A14)
A17: Priority | B17: Count
A18: P1 Apply | B18: =COUNTIF(jobs!$C:$C,A18)
A19: P2 Strong | B19: =COUNTIF(jobs!$C:$C,A19)
A20: P3 Maybe | B20: =COUNTIF(jobs!$C:$C,A20)
A21: P4 Low | B21: =COUNTIF(jobs!$C:$C,A21)
A22: Applied | B22: =COUNTIF(jobs!$C:$C,A22)
A23: Interview | B23: =COUNTIF(jobs!$C:$C,A23)
A24: Offer | B24: =COUNTIF(jobs!$C:$C,A24)
A27: Top Jobs to Apply For
A28: Priority | B28: Score | C28: Experience | D28: Status | E28: Title | F28: Company | G28: Location | H28: Closes | I28: Apply | J28: Why Claude likes it
A29: P1 Apply | B29: 8.5 | C29: Junior | D29: new | E29: Junior Python Developer | F29: Station | G29: London Area, United Kingdom | I29: Open posting | J29: Junior Python Developer title, Python, REST APIs, SQL/PostgreSQL, Django/Flask/FastAPI all match core and adjacent skills; London hybrid is within remote-ok policy.
A30: P1 Apply | B30: 8.5 | C30: Graduate/Entry | D30: new | E30: Graduate Digital Design Engineer | F30: Renesas Electronics | G30: Edinburgh, Scotland, UK | I30: Open posting | J30: FPGA/Verilog dissertation and digital design skills match RTL/HDL requirements; SystemVerilog vs Verilog minor gap.
A31: P1 Apply | B31: 8.2 | C31: Graduate/Entry | D31: new | E31: Graduate Digital Design Engineer | F31: targetjobs UK | G31: Edinburgh, Scotland, UK | I31: Open posting | J31: Graduate Digital Design Engineer matches core target role; Verilog, FPGA, Python, Git all evidenced; SystemVerilog is a minor gap.
A32: P1 Apply | B32: 8 | C32: Junior | D32: new | E32: Full Stack Engineer | F32: Fortray Global Service Limited | G32: England, United Kingdom | I32: Open posting | J32: Strong match for early-career full-stack role; Python, JS, REST APIs, Git, React, MongoDB, and Agile all present in profile.
A33: P2 Strong | B33: 7.8 | C33: Graduate/Entry | D33: new | E33: Junior Software Engineer / Computer Science Graduate (Remote) | F33: CTW Content Protection | G33: GB | I33: Open posting | J33: Python, SQL/MySQL, APIs, Docker, backend dev all directly match core skills; fully remote, salary £30-35k above floor, graduate-level role.
A34: P2 Strong | B34: 7.5 | C34: Junior | D34: new | E34: Junior Data Engineer - Integration | F34: Ocean Infinity | G34: London, England, UK | I34: Open posting | J34: Python, SQL, API integration, and backend data pipeline experience closely match this junior 0-2 year data engineering role.
A35: P2 Strong | B35: 7.5 | C35: Junior | D35: new | E35: Junior Data Engineer - Integration | F35: Ocean Infinity | G35: Southampton, England, UK | I35: Open posting | J35: Python, SQL, API integration, and backend data pipeline experience closely match this junior 0-2 year data engineering role.
A36: P2 Strong | B36: 7.5 | C36: Unspecified | D36: new | E36: GPU Datapath Design Engineer | F36: Imagination Technologies | G36: Kings Langley, England, UK | I36: Open posting | J36: FPGA/Verilog dissertation and digital design skills align well; no GPU-specific or ASIC experience, but training offered.
A37: P2 Strong | B37: 7.5 | C37: Graduate/Entry | D37: new | E37: Graduate R&D Engineer – System & Architecture | F37: Microchip Technology | G37: Whiteley, ENG, GB | I37: Open posting | J37: Graduate/early-career role matching embedded firmware, signal processing, and hardware-software interface skills from candidate's profile.
A38: P2 Strong | B38: 7.5 | C38: Unspecified | D38: new | E38: Embedded Engineer - IoT Sensors & Gateways / Smart Buildings | F38: Pressac Communications | G38: Nottingham, England, UK | I38: Open posting | J38: Strong IoT/LoRaWAN, STM32, Raspberry Pi, and embedded C/Python match; missing commercial firmware experience and specific IDE tools (STM32 IDE, Keil).
A39: P2 Strong | B39: 7.3 | C39: Unspecified | D39: new | E39: Computer Engineering | F39: Alignerr | G39: Manchester, England, UK | I39: Open posting | J39: Strong FPGA, Verilog, embedded systems, and IoT skills align; pursuing MEng meets 'Masters pursuing' requirement; freelance contract only.
A40: P2 Strong | B40: 7.2 | C40: Graduate/Entry | D40: new | E40: Graduate Engineer | F40: Spectrum IT Recruitment | G40: Fareham, England, UK | I40: Open posting | J40: Graduate Electronic Engineering role matching FPGA, Verilog, Python, DSP, and Linux skills; Fareham location is outside 60-mile radius but role suits profile well.
... A43: P2 Strong | B43: 7.2 | C43: Unspecified | D43: new | E43: Computer Engineering | F43: Alignerr | G43: Birmingham, England, UK | I43: Open posting | J43: FPGA, Verilog, embedded systems, and IoT match core JD domains; MEng satisfies degree requirement; hourly contract not a graduate role.

Sheet jobs
A1: Action | B1: Score | C1: Experience | D1: Title | E1: Company | F1: Location | G1: Salary | H1: Closes | I1: Days Left | J1: Apply | K1: Why Claude likes it | L1: Status | M1: Notes | N1: Job ID | O1: Posted | P1: Source | Q1: Matched Keywords | R1: Query | S1: Salary Min | T1: Salary Max | U1: First Seen | V1: Ranker Ver.
A2: =IF($L2="applied","Applied",IF($L2="interview","Interview",IF($L2="offer","Offer",IF($L2="rejected","Rejected",IF($L2="ignore","Ignore",IF($L2="archive","Archive",IF($L2="closed","Closed",IF($B2="","Unscored",IF(AND($B2>=8,OR($H2="",$H2-TODAY()<=14)),"P1 Apply",IF($B2>=7,"P2 Strong",IF($B2>=5,"P3 Maybe","P4 Low"))))))))))) | B2: 8.5 | C2: Junior | D2: Junior Python Developer | E2: Station | F2: London Area, United Kingdom | I2: =IF($H2="","",$H2-TODAY()) | J2: Open posting | K2: Junior Python Developer title, Python, REST APIs, SQL/PostgreSQL, Django/Flask/FastAPI all match core and adjacent skills; London hybrid is within remote-ok policy. | L2: new | N2: 46f1d6296a3c9d0be7206d78909b5b20ff30a25d | P2: jobspy | Q2: Python, REST APIs, SQL, FastAPI, Flask | R2: Junior Python Developer | U2: 46192 | V2: v2-cv-accuracy-13b988b18da8ea7d
A3: =IF($L3="applied","Applied",IF($L3="interview","Interview",IF($L3="offer","Offer",IF($L3="rejected","Rejected",IF($L3="ignore","Ignore",IF($L3="archive","Archive",IF($L3="closed","Closed",IF($B3="","Unscored",IF(AND($B3>=8,OR($H3="",$H3-TODAY()<=14)),"P1 Apply",IF($B3>=7,"P2 Strong",IF($B3>=5,"P3 Maybe","P4 Low"))))))))))) | B3: 8.5 | C3: Graduate/Entry | D3: Graduate Digital Design Engineer | E3: Renesas Electronics | F3: Edinburgh, Scotland, UK | I3: =IF($H3="","",$H3-TODAY()) | J3: Open posting | K3: FPGA/Verilog dissertation and digital design skills match RTL/HDL requirements; SystemVerilog vs Verilog minor gap. | L3: new | N3: 9384b9741d9c0cb3b1a7ef6886b9de5772942944 | O3: 46176 | P3: jobspy | Q3: Verilog, FPGA, Python, Git, digital design | R3: Graduate FPGA Engineer Verilog Vivado | U3: 46192 | V3: v2-cv-accuracy-13b988b18da8ea7d
A4: =IF($L4="applied","Applied",IF($L4="interview","Interview",IF($L4="offer","Offer",IF($L4="rejected","Rejected",IF($L4="ignore","Ignore",IF($L4="archive","Archive",IF($L4="closed","Closed",IF($B4="","Unscored",IF(AND($B4>=8,OR($H4="",$H4-TODAY()<=14)),"P1 Apply",IF($B4>=7,"P2 Strong",IF($B4>=5,"P3 Maybe","P4 Low"))))))))))) | B4: 8.2 | C4: Graduate/Entry | D4: Graduate Digital Design Engineer | E4: targetjobs UK | F4: Edinburgh, Scotland, UK | I4: =IF($H4="","",$H4-TODAY()) | J4: Open posting | K4: Graduate Digital Design Engineer matches core target role; Verilog, FPGA, Python, Git all evidenced; SystemVerilog is a minor gap. | L4: new | N4: e0f837217efc0250adb5a458ad8ad16bf518ff2a | O4: 46191 | P4: jobspy | Q4: Verilog, FPGA, Python, Git, digital design | R4: Graduate FPGA Engineer UK remote | U4: 46192 | V4: v2-cv-accuracy-13b988b18da8ea7d
A5: =IF($L5="applied","Applied",IF($L5="interview","Interview",IF($L5="offer","Offer",IF($L5="rejected","Rejected",IF($L5="ignore","Ignore",IF($L5="archive","Archive",IF($L5="closed","Closed",IF($B5="","Unscored",IF(AND($B5>=8,OR($H5="",$H5-TODAY()<=14)),"P1 Apply",IF($B5>=7,"P2 Strong",IF($B5>=5,"P3 Maybe","P4 Low"))))))))))) | B5: 8 | C5: Junior | D5: Full Stack Engineer | E5: Fortray Global Service Limited | F5: England, United Kingdom | I5: =IF($H5="","",$H5-TODAY()) | J5: Open posting | K5: Strong match for early-career full-stack role; Python, JS, REST APIs, Git, React, MongoDB, and Agile all present in profile. | L5: new | N5: 6923b68fabb4fd9d9bc9051a629b6694c6be29e7 | O5: 46188 | P5: jobspy | Q5: Python, JavaScript, REST APIs, Git, React | R5: entry level Full Stack Developer | U5: 46192 | V5: v2-cv-accuracy-13b988b18da8ea7d
A6: =IF($L6="applied","Applied",IF($L6="interview","Interview",IF($L6="offer","Offer",IF($L6="rejected","Rejected",IF($L6="ignore","Ignore",IF($L6="archive","Archive",IF($L6="closed","Closed",IF($B6="","Unscored",IF(AND($B6>=8,OR($H6="",$H6-TODAY()<=14)),"P1 Apply",IF($B6>=7,"P2 Strong",IF($B6>=5,"P3 Maybe","P4 Low"))))))))))) | B6: 7.8 | C6: Graduate/Entry | D6: Junior Software Engineer / Computer Science Graduate (Remote) | E6: CTW Content Protection | F6: GB | I6: =IF($H6="","",$H6-TODAY()) | J6: Open posting | K6: Python, SQL/MySQL, APIs, Docker, backend dev all directly match core skills; fully remote, salary £30-35k above floor, graduate-level role. | L6: new | N6: d0d916f9adcdabb6ccab921b95bc4589da3e3c50 | O6: 46188 | P6: jobspy | Q6: Python, MySQL, Docker, API integration, SQL | R6: Platform Engineer backend Python SQL graduate | U6: 46192 | V6: v2-cv-accuracy-13b988b18da8ea7d
A7: =IF($L7="applied","Applied",IF($L7="interview","Interview",IF($L7="offer","Offer",IF($L7="rejected","Rejected",IF($L7="ignore","Ignore",IF($L7="archive","Archive",IF($L7="closed","Closed",IF($B7="","Unscored",IF(AND($B7>=8,OR($H7="",$H7-TODAY()<=14)),"P1 Apply",IF($B7>=7,"P2 Strong",IF($B7>=5,"P3 Maybe","P4 Low"))))))))))) | B7: 7.5 | C7: Junior | D7: Junior Data Engineer - Integration | E7: Ocean Infinity | F7: London, England, UK | I7: =IF($H7="","",$H7-TODAY()) | J7: Open posting | K7: Python, SQL, API integration, and backend data pipeline experience closely match this junior 0-2 year data engineering role. | L7: new | N7: 1fe209d1974bbaeb8dc5366467e400e6e0ef17db | P7: jobspy | Q7: Python, SQL, API integration, MySQL, backend development | R7: Junior Data Engineer Python SQL MySQL | U7: 46195 | V7: v2-cv-accuracy-13b988b18da8ea7d
A8: =IF($L8="applied","Applied",IF($L8="interview","Interview",IF($L8="offer","Offer",IF($L8="rejected","Rejected",IF($L8="ignore","Ignore",IF($L8="archive","Archive",IF($L8="closed","Closed",IF($B8="","Unscored",IF(AND($B8>=8,OR($H8="",$H8-TODAY()<=14)),"P1 Apply",IF($B8>=7,"P2 Strong",IF($B8>=5,"P3 Maybe","P4 Low"))))))))))) | B8: 7.5 | C8: Junior | D8: Junior Data Engineer - Integration | E8: Ocean Infinity | F8: Southampton, England, UK | I8: =IF($H8="","",$H8-TODAY()) | J8: Open posting | K8: Python, SQL, API integration, and backend data pipeline experience closely match this junior 0-2 year data engineering role. | L8: new | N8: 06819d866830536a2f612df53be3d32627089eb3 | P8: jobspy | Q8: Python, SQL, API integration, MySQL, backend development | R8: Junior Data Engineer Python SQL MySQL | U8: 46195 | V8: v2-cv-accuracy-13b988b18da8ea7d
A9: =IF($L9="applied","Applied",IF($L9="interview","Interview",IF($L9="offer","Offer",IF($L9="rejected","Rejected",IF($L9="ignore","Ignore",IF($L9="archive","Archive",IF($L9="closed","Closed",IF($B9="","Unscored",IF(AND($B9>=8,OR($H9="",$H9-TODAY()<=14)),"P1 Apply",IF($B9>=7,"P2 Strong",IF($B9>=5,"P3 Maybe","P4 Low"))))))))))) | B9: 7.5 | C9: Unspecified | D9: GPU Datapath Design Engineer | E9: Imagination Technologies | F9: Kings Langley, England, UK | I9: =IF($H9="","",$H9-TODAY()) | J9: Open posting | K9: FPGA/Verilog dissertation and digital design skills align well; no GPU-specific or ASIC experience, but training offered. | L9: new | N9: d00bbbc4ca69b9bb8923cb0f10a4b434ea348ef2 | O9: 46178 | P9: jobspy | Q9: Verilog, FPGA, Python, digital design, DSP | R9: Graduate FPGA Engineer Verilog Vivado | U9: 46194 | V9: v2-cv-accuracy-13b988b18da8ea7d
A10: =IF($L10="applied","Applied",IF($L10="interview","Interview",IF($L10="offer","Offer",IF($L10="rejected","Rejected",IF($L10="ignore","Ignore",IF($L10="archive","Archive",IF($L10="closed","Closed",IF($B10="","Unscored",IF(AND($B10>=8,OR($H10="",$H10-TODAY()<=14)),"P1 Apply",IF($B10>=7,"P2 Strong",IF($B10>=5,"P3 Maybe","P4 Low"))))))))))) | B10: 7.5 | C10: Graduate/Entry | D10: Graduate R&D Engineer – System & Architecture | E10: Microchip Technology | F10: Whiteley, ENG, GB | I10: =IF($H10="","",$H10-TODAY()) | J10: Open posting | K10: Graduate/early-career role matching embedded firmware, signal processing, and hardware-software interface skills from candidate's profile. | L10: new | N10: 739a7a4fbff2e88cb93edf982e7e4550aea7d26c | O10: 46190 | P10: jobspy | Q10: embedded systems, C, STM32, signal processing, Python | R10: Graduate Systems Engineer embedded hardware software | U10: 46192 | V10: v2-cv-accuracy-13b988b18da8ea7d
A11: =IF($L11="applied","Applied",IF($L11="interview","Interview",IF($L11="offer","Offer",IF($L11="rejected","Rejected",IF($L11="ignore","Ignore",IF($L11="archive","Archive",IF($L11="closed","Closed",IF($B11="","Unscored",IF(AND($B11>=8,OR($H11="",$H11-TODAY()<=14)),"P1 Apply",IF($B11>=7,"P2 Strong",IF($B11>=5,"P3 Maybe","P4 Low"))))))))))) | B11: 7.5 | C11: Unspecified | D11: Embedded Engineer - IoT Sensors & Gateways / Smart Buildings | E11: Pressac Communications | F11: Nottingham, England, UK | I11: =IF($H11="","",$H11-TODAY()) | J11: Open posting | K11: Strong IoT/LoRaWAN, STM32, Raspberry Pi, and embedded C/Python match; missing commercial firmware experience and specific IDE tools (STM32 IDE, Keil). | L11: new | N11: aae6ade6b34a2ad208b86b4d2dad8ba09445fbbe | O11: 46189 | P11: jobspy | Q11: LoRaWAN, STM32, Raspberry Pi, Python, embedded systems | R11: Junior Embedded Software Engineer STM32 | U11: 46192 | V11: v2-cv-accuracy-13b988b18da8ea7d
A12: =IF($L12="applied","Applied",IF($L12="interview","Interview",IF($L12="offer","Offer",IF($L12="rejected","Rejected",IF($L12="ignore","Ignore",IF($L12="archive","Archive",IF($L12="closed","Closed",IF($B12="","Unscored",IF(AND($B12>=8,OR($H12="",$H12-TODAY()<=14)),"P1 Apply",IF($B12>=7,"P2 Strong",IF($B12>=5,"P3 Maybe","P4 Low"))))))))))) | B12: 7.3 | C12: Unspecified | D12: Computer Engineering | E12: Alignerr | F12: Manchester, England, UK | I12: =IF($H12="","",$H12-TODAY()) | J12: Open posting | K12: Strong FPGA, Verilog, embedded systems, and IoT skills align; pursuing MEng meets 'Masters pursuing' requirement; freelance contract only. | L12: new | N12: 925fcb619fc33cf24860169a4c291257d865a046 | O12: 46189 | P12: jobspy | Q12: FPGA, Verilog, embedded systems, IoT, digital design | R12: Graduate Computer Engineer digital design | U12: 46194 | V12: v2-cv-accuracy-13b988b18da8ea7d
A13: =IF($L13="applied","Applied",IF($L13="interview","Interview",IF($L13="offer","Offer",IF($L13="rejected","Rejected",IF($L13="ignore","Ignore",IF($L13="archive","Archive",IF($L13="closed","Closed",IF($B13="","Unscored",IF(AND($B13>=8,OR($H13="",$H13-TODAY()<=14)),"P1 Apply",IF($B13>=7,"P2 Strong",IF($B13>=5,"P3 Maybe","P4 Low"))))))))))) | B13: 7.2 | C13: Graduate/Entry | D13: Graduate Engineer | E13: Spectrum IT Recruitment | F13: Fareham, England, UK | I13: =IF($H13="","",$H13-TODAY()) | J13: Open posting | K13: Graduate Electronic Engineering role matching FPGA, Verilog, Python, DSP, and Linux skills; Fareham location is outside 60-mile radius but role suits profile well. | L13: new | N13: 743e2618064c9780f0dbf2e7134ea6741dfe6ce1 | O13: 46197 | P13: jobspy | Q13: FPGA, Verilog, Python, digital design, signal processing | R13: Graduate Signal Processing Engineer DSP FPGA | U13: 46199 | V13: v2-cv-accuracy-13b988b18da8ea7d
A14: =IF($L14="applied","Applied",IF($L14="interview","Interview",IF($L14="offer","Offer",IF($L14="rejected","Rejected",IF($L14="ignore","Ignore",IF($L14="archive","Archive",IF($L14="closed","Closed",IF($B14="","Unscored",IF(AND($B14>=8,OR($H14="",$H14-TODAY()<=14)),"P1 Apply",IF($B14>=7,"P2 Strong",IF($B14>=5,"P3 Maybe","P4 Low"))))))))))) | B14: 7.2 | C14: Unspecified | D14: Computer Engineering Expert - AI Content Specialist | E14: Alignerr | F14: Oxford, England, UK | I14: =IF($H14="","",$H14-TODAY()) | J14: Open posting | K14: MEng in ECE (pursuing Masters-level), FPGA/Verilog/embedded systems match well; contract/hourly role not a graduate permanent position. | L14: new | N14: 5b302bdc4392578b1e67cf6b53ca56f4c547210d | O14: 46191 | P14: jobspy | Q14: FPGA, Verilog, embedded systems, digital design, SolidWorks | R14: Graduate Computer Engineer digital design | U14: 46194 | V14: v2-cv-accuracy-13b988b18da8ea7d
A15: =IF($L15="applied","Applied",IF($L15="interview","Interview",IF($L15="offer","Offer",IF($L15="rejected","Rejected",IF($L15="ignore","Ignore",IF($L15="archive","Archive",IF($L15="closed","Closed",IF($B15="","Unscored",IF(AND($B15>=8,OR($H15="",$H15-TODAY()<=14)),"P1 Apply",IF($B15>=7,"P2 Strong",IF($B15>=5,"P3 Maybe","P4 Low"))))))))))) | B15: 7.2 | C15: Unspecified | D15: Computer Engineering Expert - AI Content Specialist | E15: Alignerr | F15: Birmingham, England, UK | I15: =IF($H15="","",$H15-TODAY()) | J15: Open posting | K15: MEng in ECE (pursuing Masters-level), FPGA/Verilog/embedded systems match well; contract/hourly role not a graduate permanent position. | L15: new | N15: 4ada3c9d583603a2f905958297b3e23d04acb4bf | O15: 46191 | P15: jobspy | Q15: FPGA, Verilog, embedded systems, digital design, SolidWorks | R15: Graduate Computer Engineer digital design | U15: 46194 | V15: v2-cv-accuracy-13b988b18da8ea7d
A16: =IF($L16="applied","Applied",IF($L16="interview","Interview",IF($L16="offer","Offer",IF($L16="rejected","Rejected",IF($L16="ignore","Ignore",IF($L16="archive","Archive",IF($L16="closed","Closed",IF($B16="","Unscored",IF(AND($B16>=8,OR($H16="",$H16-TODAY()<=14)),"P1 Apply",IF($B16>=7,"P2 Strong",IF($B16>=5,"P3 Maybe","P4 Low"))))))))))) | B16: 7.2 | C16: Unspecified | D16: Computer Engineering | E16: Alignerr | F16: Birmingham, England, UK | I16: =IF($H16="","",$H16-TODAY()) | J16: Open posting | K16: FPGA, Verilog, embedded systems, and IoT match core JD domains; MEng satisfies degree requirement; hourly contract not a graduate role. | L16: new | N16: 293e437b19ac5c627215558adf56744130a51fb4 | O16: 46188 | P16: jobspy | Q16: FPGA, Verilog, embedded systems, IoT, SolidWorks | R16: Graduate Computer Engineer digital design | U16: 46194 | V16: v2-cv-accuracy-13b988b18da8ea7d
A17: =IF($L17="applied","Applied",IF($L17="interview","Interview",IF($L17="offer","Offer",IF($L17="rejected","Rejected",IF($L17="ignore","Ignore",IF($L17="archive","Archive",IF($L17="closed","Closed",IF($B17="","Unscored",IF(AND($B17>=8,OR($H17="",$H17-TODAY()<=14)),"P1 Apply",IF($B17>=7,"P2 Strong",IF($B17>=5,"P3 Maybe","P4 Low"))))))))))) | B17: 7.2 | C17: Unspecified | D17: Computer Engineering | E17: Alignerr | F17: Edinburgh, Scotland, UK | I17: =IF($H17="","",$H17-TODAY()) | J17: Open posting | K17: FPGA, Verilog, embedded systems, and IoT match core JD domains; MEng satisfies degree requirement; hourly contract not a graduate role. | L17: new | N17: 6b8e2c2d38d8288a7329fdc7855bae1467ecb3a1 | O17: 46188 | P17: jobspy | Q17: FPGA, Verilog, embedded systems, IoT, SolidWorks | R17: Graduate Computer Engineer digital design | U17: 46194 | V17: v2-cv-accuracy-13b988b18da8ea7d
A18: =IF($L18="applied","Applied",IF($L18="interview","Interview",IF($L18="offer","Offer",IF($L18="rejected","Rejected",IF($L18="ignore","Ignore",IF($L18="archive","Archive",IF($L18="closed","Closed",IF($B18="","Unscored",IF(AND($B18>=8,OR($H18="",$H18-TODAY()<=14)),"P1 Apply",IF($B18>=7,"P2 Strong",IF($B18>=5,"P3 Maybe","P4 Low"))))))))))) | B18: 7.2 | C18: Junior | D18: Digital Design Engineer (AP) | E18: Cirrus Logic | F18: Edinburgh, Scotland, UK | I18: =IF($H18="","",$H18-TODAY()) | J18: Open posting | K18: Verilog and FPGA skills match well; gaps in SystemVerilog, synthesis flows, CDC tools, and Edinburgh location adds friction. | L18: new | N18: a1cc467249a00aa9b92d12e7648d43e8f69f41e6 | O18: 46182 | P18: jobspy | Q18: Verilog, FPGA, Vivado, digital design, DSP | R18: Graduate Digital Design Engineer FPGA | U18: 46193 | V18: v2-cv-accuracy-13b988b18da8ea7d
A19: =IF($L19="applied","Applied",IF($L19="interview","Interview",IF($L19="offer","Offer",IF($L19="rejected","Rejected",IF($L19="ignore","Ignore",IF($L19="archive","Archive",IF($L19="closed","Closed",IF($B19="","Unscored",IF(AND($B19>=8,OR($H19="",$H19-TODAY()<=14)),"P1 Apply",IF($B19>=7,"P2 Strong",IF($B19>=5,"P3 Maybe","P4 Low"))))))))))) | B19: 7.2 | C19: Senior/Lead | D19: Software Engineer | E19: Crowder Consulting | F19: Birkenhead, ENG, GB | I19: =IF($H19="","",$H19-TODAY()) | J19: Open posting | K19: Python, SQL, Docker, REST APIs, and backend dev match well; no Java or cloud-platform experience evident in profile. | L19: new | N19: 8bae9f5a399a163efc3fbe14a19862a5fa85f27a | O19: 46183 | P19: jobspy | Q19: Python, SQL, Docker, MySQL, REST APIs | R19: Graduate Software Engineer Python Docker | U19: 46193 | V19: v2-cv-accuracy-13b988b18da8ea7d
A20: =IF($L20="applied","Applied",IF($L20="interview","Interview",IF($L20="offer","Offer",IF($L20="rejected","Rejected",IF($L20="ignore","Ignore",IF($L20="archive","Archive",IF($L20="closed","Closed",IF($B20="","Unscored",IF(AND($B20>=8,OR($H20="",$H20-TODAY()<=14)),"P1 Apply",IF($B20>=7,"P2 Strong",IF($B20>=5,"P3 Maybe","P4 Low"))))))))))) | B20: 7.2 | C20: Mid-level | D20: Verification Engineer (f/m/d) | E20: Renesas | F20: Edinburgh, SCT, GB | I20: =IF($H20="","",$H20-TODAY()) | J20: Open posting | K20: FPGA dissertation, Verilog, digital design, and Git strongly match; SystemVerilog/UVM not explicitly evidenced but role accepts academic FPGA experience. | L20: new | N20: 656ebc383881b04d4b39edc8c7c8498c5a04a43f | O20: 46185 | P20: jobspy | Q20: Verilog, FPGA, digital design, Python, Git | R20: Digital Design Engineer FPGA Verilog | U20: 46193 | V20: v2-cv-accuracy-13b988b18da8ea7d
A21: =IF($L21="applied","Applied",IF($L21="interview","Interview",IF($L21="offer","Offer",IF($L21="rejected","Rejected",IF($L21="ignore","Ignore",IF($L21="archive","Archive",IF($L21="closed","Closed",IF($B21="","Unscored",IF(AND($B21>=8,OR($H21="",$H21-TODAY()<=14)),"P1 Apply",IF($B21>=7,"P2 Strong",IF($B21>=5,"P3 Maybe","P4 Low"))))))))))) | B21: 7 | C21: Mid-level | D21: Embedded Software Engineer | E21: Archangel Autonomy | F21: Oxford, England, UK | I21: =IF($H21="","",$H21-TODAY()) | J21: Open posting | K21: LoRaWAN IoT and embedded systems match well; role requires commercial C/C++ firmware delivery experience which exceeds the candidate's internship-level evidence. | L21: new | N21: a975ebe001a211a85c04582006e39137d419e9a4 | P21: jobspy | Q21: LoRaWAN, IoT, embedded systems, Raspberry Pi, Python | R21: Junior Firmware Engineer STM32 C Python | U21: 46199 | V21: v2-cv-accuracy-13b988b18da8ea7d
A22: =IF($L22="applied","Applied",IF($L22="interview","Interview",IF($L22="offer","Offer",IF($L22="rejected","Rejected",IF($L22="ignore","Ignore",IF($L22="archive","Archive",IF($L22="closed","Closed",IF($B22="","Unscored",IF(AND($B22>=8,OR($H22="",$H22-TODAY()<=14)),"P1 Apply",IF($B22>=7,"P2 Strong",IF($B22>=5,"P3 Maybe","P4 Low"))))))))))) | B22: 7 | C22: Junior | D22: Manchester - Junior Developer - Elevate Programme | E22: Vantage Point Global | F22: Manchester, England, UK | I22: =IF($H22="","",$H22-TODAY()) | J22: Open posting | K22: Junior developer role matching experience level; JavaScript, APIs, SQL, and databases align well, though enterprise/consultancy platform focus is a gap. | L22: new | N22: 49d744a689360e4fd2e2433a67a0579f5163bc2a | O22: 46190 | P22: jobspy | Q22: JavaScript, SQL, API integration, Git, backend development | R22: Graduate Verification Engineer digital design | U22: 46194 | V22: v2-cv-accuracy-13b988b18da8ea7d
A23: =IF($L23="applied","Applied",IF($L23="interview","Interview",IF($L23="offer","Offer",IF($L23="rejected","Rejected",IF($L23="ignore","Ignore",IF($L23="archive","Archive",IF($L23="closed","Closed",IF($B23="","Unscored",IF(AND($B23>=8,OR($H23="",$H23-TODAY()<=14)),"P1 Apply",IF($B23>=7,"P2 Strong",IF($B23>=5,"P3 Maybe","P4 Low"))))))))))) | B23: 7 | C23: Junior | D23: Junior Full Stack Developer | E23: Haystack | F23: London, England, UK | I23: =IF($H23="","",$H23-TODAY()) | J23: Open posting | K23: JavaScript, React, Node.js, APIs and AWS match adjacent skills; fully remote suits profile; limited JD detail on seniority requirements. | L23: new | N23: eacb8ba7c567f6e07699dc4724081786e55aecf1 | P23: jobspy | Q23: JavaScript, React, Node.js, REST APIs, AWS | R23: junior Graduate Software Developer | U23: 46192 | V23: v2-cv-accuracy-13b988b18da8ea7d
A24: =IF($L24="applied","Applied",IF($L24="interview","Interview",IF($L24="offer","Offer",IF($L24="rejected","Rejected",IF($L24="ignore","Ignore",IF($L24="archive","Archive",IF($L24="closed","Closed",IF($B24="","Unscored",IF(AND($B24>=8,OR($H24="",$H24-TODAY()<=14)),"P1 Apply",IF($B24>=7,"P2 Strong",IF($B24>=5,"P3 Maybe","P4 Low"))))))))))) | B24: 7 | C24: Mid-level | D24: Software Engineer - Graduates Considered | E24: RedTech Recruitment | F24: London Area, United Kingdom | I24: =IF($H24="","",$H24-TODAY()) | J24: Open posting | K24: Graduate-level Python role matching core skills; Cambridge/London location is outside 60-mile radius but hybrid is partial mitigation. | L24: new | N24: 845cfaa77fa2493790127833cc58821b2ef358c5 | P24: jobspy | Q24: Python, Docker, JavaScript, Git | R24: Junior Python Developer Docker Kubernetes Sheffield | U24: 46192 | V24: v2-cv-accuracy-13b988b18da8ea7d
A25: =IF($L25="applied","Applied",IF($L25="interview","Interview",IF($L25="offer","Offer",IF($L25="rejected","Rejected",IF($L25="ignore","Ignore",IF($L25="archive","Archive",IF($L25="closed","Closed",IF($B25="","Unscored",IF(AND($B25>=8,OR($H25="",$H25-TODAY()<=14)),"P1 Apply",IF($B25>=7,"P2 Strong",IF($B25>=5,"P3 Maybe","P4 Low"))))))))))) | B25: 7 | C25: Graduate/Entry | D25: Graduate Validation Engineer | E25: Cirrus Logic | F25: Edinburgh, Scotland, UK | I25: =IF($H25="","",$H25-TODAY()) | J25: Open posting | K25: Graduate validation role suits experience level; Python, FPGA, digital/mixed-signal debugging align, though PCB design and LabVIEW are minor gaps. | L25: new | N25: 3cd185f1454f7f595f7f6679e2076489236211aa | O25: 46170 | P25: jobspy | Q25: Python, FPGA, digital design, embedded systems, signal processing | R25: Graduate Verification Engineer Verilog digital | U25: 46192 | V25: v2-cv-accuracy-13b988b18da8ea7d
A26: =IF($L26="applied","Applied",IF($L26="interview","Interview",IF($L26="offer","Offer",IF($L26="rejected","Rejected",IF($L26="ignore","Ignore",IF($L26="archive","Archive",IF($L26="closed","Closed",IF($B26="","Unscored",IF(AND($B26>=8,OR($H26="",$H26-TODAY()<=14)),"P1 Apply",IF($B26>=7,"P2 Strong",IF($B26>=5,"P3 Maybe","P4 Low"))))))))))) | B26: 6.5 | C26: Graduate/Entry | D26: Graduate R&D Engineer – System & Architecture | E26: Microchip Technology Inc. | F26: Whiteley, England, UK | I26: =IF($H26="","",$H26-TODAY()) | J26: Open posting | K26: Embedded firmware and signal processing align well; analogue/capacitive sensing expertise is a gap not evidenced in profile. | L26: new | N26: 1bba1621a27c81939832e15f49a5a0f64e74cb5e | P26: jobspy | Q26: embedded systems, digital design, signal processing, C, DSP | R26: Graduate Systems Engineer hardware software Sheffield | U26: 46196 | V26: v2-cv-accuracy-13b988b18da8ea7d
A27: =IF($L27="applied","Applied",IF($L27="interview","Interview",IF($L27="offer","Offer",IF($L27="rejected","Rejected",IF($L27="ignore","Ignore",IF($L27="archive","Archive",IF($L27="closed","Closed",IF($B27="","Unscored",IF(AND($B27>=8,OR($H27="",$H27-TODAY()<=14)),"P1 Apply",IF($B27>=7,"P2 Strong",IF($B27>=5,"P3 Maybe","P4 Low"))))))))))) | B27: 6.5 | C27: Senior/Lead | D27: Software Engineer | E27: Venn Telecom | F27: Exeter, England, UK | I27: =IF($H27="","",$H27-TODAY()) | J27: Open posting | K27: Python, SQL, Docker, Node.js, and backend dev match well, but Exeter location is outside 60-mile radius and no cloud platform experience evidenced. | L27: new | N27: ecebc3e7669434abafc4e4ebf5461fd3200ec838 | O27: 46183 | P27: jobspy | Q27: Python, SQL, Docker, MySQL, Node.js | R27: Graduate Software Engineer Python backend | U27: 46195 | V27: v2-cv-accuracy-13b988b18da8ea7d
A28: =IF($L28="applied","Applied",IF($L28="interview","Interview",IF($L28="offer","Offer",IF($L28="rejected","Rejected",IF($L28="ignore","Ignore",IF($L28="archive","Archive",IF($L28="closed","Closed",IF($B28="","Unscored",IF(AND($B28>=8,OR($H28="",$H28-TODAY()<=14)),"P1 Apply",IF($B28>=7,"P2 Strong",IF($B28>=5,"P3 Maybe","P4 Low"))))))))))) | B28: 6.5 | C28: Unspecified | D28: Computer Engineering | E28: Alignerr | F28: Cambridge, England, UK | I28: =IF($H28="","",$H28-TODAY()) | J28: Open posting | K28: FPGA/Verilog dissertation, embedded systems, and digital design directly match core duties; MEng pursuing satisfies advanced degree requirement. | L28: new | N28: c3110f690efa5200346d49a4b255139a6e4b9afb | O28: 46192 | P28: jobspy | Q28: FPGA, Verilog, embedded systems, digital design, SolidWorks | R28: Graduate Computer Engineer digital design | U28: 46194 | V28: v2-cv-accuracy-13b988b18da8ea7d
A29: =IF($L29="applied","Applied",IF($L29="interview","Interview",IF($L29="offer","Offer",IF($L29="rejected","Rejected",IF($L29="ignore","Ignore",IF($L29="archive","Archive",IF($L29="closed","Closed",IF($B29="","Unscored",IF(AND($B29>=8,OR($H29="",$H29-TODAY()<=14)),"P1 Apply",IF($B29>=7,"P2 Strong",IF($B29>=5,"P3 Maybe","P4 Low"))))))))))) | B29: 6.5 | C29: Unspecified | D29: Computer Engineering Expert - AI Content Specialist | E29: Alignerr | F29: London, England, UK | I29: =IF($H29="","",$H29-TODAY()) | J29: Open posting | K29: Same role as above; FPGA, Verilog, embedded systems, and digital logic design strongly align with content specialist requirements. | L29: new | N29: 5ca07c5cf62fb84fc42f4f548049e21619607a4f | O29: 46191 | P29: jobspy | Q29: FPGA, Verilog, embedded systems, digital design, SolidWorks | R29: Graduate Computer Engineer digital design | U29: 46194 | V29: v2-cv-accuracy-13b988b18da8ea7d
A30: =IF($L30="applied","Applied",IF($L30="interview","Interview",IF($L30="offer","Offer",IF($L30="rejected","Rejected",IF($L30="ignore","Ignore",IF($L30="archive","Archive",IF($L30="closed","Closed",IF($B30="","Unscored",IF(AND($B30>=8,OR($H30="",$H30-TODAY()<=14)),"P1 Apply",IF($B30>=7,"P2 Strong",IF($B30>=5,"P3 Maybe","P4 Low"))))))))))) | B30: 6.5 | C30: Unspecified | D30: Computer Engineering | E30: Alignerr | F30: Oxford, England, UK | I30: =IF($H30="","",$H30-TODAY()) | J30: Open posting | K30: FPGA, Verilog, embedded systems, and MEng (pursuing) match well; contract/hourly pay and non-UK currency are minor concerns. | L30: new | N30: 60dec6dfcbf74ff2e76b42a15d50a130e991e554 | O30: 46188 | P30: jobspy | Q30: FPGA, Verilog, embedded systems, digital design, SolidWorks | R30: Graduate Computer Engineer digital design | U30: 46194 | V30: v2-cv-accuracy-13b988b18da8ea7d
A31: =IF($L31="applied","Applied",IF($L31="interview","Interview",IF($L31="offer","Offer",IF($L31="rejected","Rejected",IF($L31="ignore","Ignore",IF($L31="archive","Archive",IF($L31="closed","Closed",IF($B31="","Unscored",IF(AND($B31>=8,OR($H31="",$H31-TODAY()<=14)),"P1 Apply",IF($B31>=7,"P2 Strong",IF($B31>=5,"P3 Maybe","P4 Low"))))))))))) | B31: 6.5 | C31: Unspecified | D31: Computer Engineering | E31: Alignerr | F31: London, England, UK | I31: =IF($H31="","",$H31-TODAY()) | J31: Open posting | K31: FPGA, Verilog, embedded systems, and MEng (pursuing) match well; contract/hourly pay and non-UK currency are minor concerns. | L31: new | N31: 93cab7b860353c713f6fdb5853b08a434ddc3dfa | O31: 46188 | P31: jobspy | Q31: FPGA, Verilog, embedded systems, digital design, SolidWorks | R31: Graduate Computer Engineer digital design | U31: 46194 | V31: v2-cv-accuracy-13b988b18da8ea7d
A32: =IF($L32="applied","Applied",IF($L32="interview","Interview",IF($L32="offer","Offer",IF($L32="rejected","Rejected",IF($L32="ignore","Ignore",IF($L32="archive","Archive",IF($L32="closed","Closed",IF($B32="","Unscored",IF(AND($B32>=8,OR($H32="",$H32-TODAY()<=14)),"P1 Apply",IF($B32>=7,"P2 Strong",IF($B32>=5,"P3 Maybe","P4 Low"))))))))))) | B32: 6.5 | C32: Unspecified | D32: Computer Engineering | E32: Alignerr | F32: Christchurch, England, UK | I32: =IF($H32="","",$H32-TODAY()) | J32: Open posting | K32: FPGA, Verilog, embedded systems, and MEng (pursuing) match well; contract/hourly pay and non-UK currency are minor concerns. | L32: new | N32: 05930b5225024aa12a5a26f832ac99f535a7bbdb | O32: 46188 | P32: jobspy | Q32: FPGA, Verilog, embedded systems, digital design, SolidWorks | R32: Graduate Computer Engineer digital design | U32: 46194 | V32: v2-cv-accuracy-13b988b18da8ea7d
A33: =IF($L33="applied","Applied",IF($L33="interview","Interview",IF($L33="offer","Offer",IF($L33="rejected","Rejected",IF($L33="ignore","Ignore",IF($L33="archive","Archive",IF($L33="closed","Closed",IF($B33="","Unscored",IF(AND($B33>=8,OR($H33="",$H33-TODAY()<=14)),"P1 Apply",IF($B33>=7,"P2 Strong",IF($B33>=5,"P3 Maybe","P4 Low"))))))))))) | B33: 6.5 | C33: Unspecified | D33: Computer Engineering | E33: Alignerr | F33: Glasgow, Scotland, UK | I33: =IF($H33="","",$H33-TODAY()) | J33: Open posting | K33: FPGA, Verilog, embedded systems, and MEng (pursuing) match well; contract/hourly pay and non-UK currency are minor concerns. | L33: new | N33: 4eb8339c75fe77592d166b21e5510f46cc972a06 | O33: 46188 | P33: jobspy | Q33: FPGA, Verilog, embedded systems, digital design, SolidWorks | R33: Graduate Computer Engineer digital design | U33: 46194 | V33: v2-cv-accuracy-13b988b18da8ea7d
A34: =IF($L34="applied","Applied",IF($L34="interview","Interview",IF($L34="offer","Offer",IF($L34="rejected","Rejected",IF($L34="ignore","Ignore",IF($L34="archive","Archive",IF($L34="closed","Closed",IF($B34="","Unscored",IF(AND($B34>=8,OR($H34="",$H34-TODAY()<=14)),"P1 Apply",IF($B34>=7,"P2 Strong",IF($B34>=5,"P3 Maybe","P4 Low"))))))))))) | B34: 6.5 | C34: Unspecified | D34: Computer Engineering | E34: Alignerr | I34: =IF($H34="","",$H34-TODAY()) | J34: Open posting | K34: FPGA, Verilog, embedded systems, and MEng (pursuing) match well; contract/hourly pay and non-UK currency are minor concerns. | L34: new | N34: 8163300ff098715cd31228ae69ab909e61757e1e | O34: 46188 | P34: jobspy | Q34: FPGA, Verilog, embedded systems, digital design, SolidWorks | R34: Graduate Computer Engineer digital design | U34: 46194 | V34: v2-cv-accuracy-13b988b18da8ea7d
A35: =IF($L35="applied","Applied",IF($L35="interview","Interview",IF($L35="offer","Offer",IF($L35="rejected","Rejected",IF($L35="ignore","Ignore",IF($L35="archive","Archive",IF($L35="closed","Closed",IF($B35="","Unscored",IF(AND($B35>=8,OR($H35="",$H35-TODAY()<=14)),"P1 Apply",IF($B35>=7,"P2 Strong",IF($B35>=5,"P3 Maybe","P4 Low"))))))))))) | B35: 6.5 | C35: Senior/Lead | D35: Software Engineer | E35: Metric | F35: London Area, United Kingdom | I35: =IF($H35="","",$H35-TODAY()) | J35: Open posting | K35: Python, Linux, FPGA, embedded systems, and CI/CD match well; lacks production systems experience and C++/Rust, seniority framing slightly above graduate level. | L35: new | N35: 356bcab80ecc693618cdb8180e9db31fdb9f92f8 | O35: 46174 | P35: jobspy | Q35: Python, FPGA, embedded systems, Git, CI/CD | R35: Embedded Software Engineer graduate C Python | U35: 46194 | V35: v2-cv-accuracy-13b988b18da8ea7d
A36: =IF($L36="applied","Applied",IF($L36="interview","Interview",IF($L36="offer","Offer",IF($L36="rejected","Rejected",IF($L36="ignore","Ignore",IF($L36="archive","Archive",IF($L36="closed","Closed",IF($B36="","Unscored",IF(AND($B36>=8,OR($H36="",$H36-TODAY()<=14)),"P1 Apply",IF($B36>=7,"P2 Strong",IF($B36>=5,"P3 Maybe","P4 Low"))))))))))) | B36: 6.5 | C36: Unspecified | D36: Embedded System Engineer | E36: Open Cosmos | F36: Harwell, England, UK | I36: =IF($H36="","",$H36-TODAY()) | J36: Open posting | K36: Verilog, FPGA, and embedded systems match well but C/C++ RTOS proficiency and fault-tolerant space-grade design are gaps. | L36: new | N36: f799d76cb9290d22f3ddec958fb63c3911d1857e | O36: 46181 | P36: jobspy | Q36: Verilog, FPGA, embedded systems, Vivado, sensor integration | R36: Graduate Signal Processing Engineer DSP | U36: 46193 | V36: v2-cv-accuracy-13b988b18da8ea7d
A37: =IF($L37="applied","Applied",IF($L37="interview","Interview",IF($L37="offer","Offer",IF($L37="rejected","Rejected",IF($L37="ignore","Ignore",IF($L37="archive","Archive",IF($L37="closed","Closed",IF($B37="","Unscored",IF(AND($B37>=8,OR($H37="",$H37-TODAY()<=14)),"P1 Apply",IF($B37>=7,"P2 Strong",IF($B37>=5,"P3 Maybe","P4 Low"))))))))))) | B37: 6.5 | C37: Junior | D37: Junior Platform Engineer | E37: Bud Systems | F37: Bristol, ENG, GB | I37: =IF($H37="","",$H37-TODAY()) | J37: Open posting | K37: Good match on Python, SQL, Docker, Kubernetes, Git and CI/CD; SC Clearance eligibility requirement is a potential flag not confirmed in profile. | L37: new | N37: 5b010348e00166189f6e1862022ed946d204e1bf | O37: 46181 | P37: jobspy | Q37: Python, SQL, Docker, Kubernetes, Git | R37: Junior Python Developer SQL Docker | U37: 46193 | V37: v2-cv-accuracy-13b988b18da8ea7d
A38: =IF($L38="applied","Applied",IF($L38="interview","Interview",IF($L38="offer","Offer",IF($L38="rejected","Rejected",IF($L38="ignore","Ignore",IF($L38="archive","Archive",IF($L38="closed","Closed",IF($B38="","Unscored",IF(AND($B38>=8,OR($H38="",$H38-TODAY()<=14)),"P1 Apply",IF($B38>=7,"P2 Strong",IF($B38>=5,"P3 Maybe","P4 Low"))))))))))) | B38: 6.5 | C38: Unspecified | D38: Software Developer | E38: nan | F38: Harrow, ENG, GB | I38: =IF($H38="","",$H38-TODAY()) | J38: Open posting | K38: Python, SQL, Docker, Kubernetes, REST APIs, and JavaScript match well; fintech/banking domain and OAuth2/compliance experience are gaps. | L38: new | N38: e0a174ff327047b93e55ad030810b3af8a33f165 | O38: 46191 | P38: jobspy | Q38: Python, SQL, Docker, Kubernetes, JavaScript | R38: Platform Engineer Docker Kubernetes Python | U38: 46193 | V38: v2-cv-accuracy-13b988b18da8ea7d
A39: =IF($L39="applied","Applied",IF($L39="interview","Interview",IF($L39="offer","Offer",IF($L39="rejected","Rejected",IF($L39="ignore","Ignore",IF($L39="archive","Archive",IF($L39="closed","Closed",IF($B39="","Unscored",IF(AND($B39>=8,OR($H39="",$H39-TODAY()<=14)),"P1 Apply",IF($B39>=7,"P2 Strong",IF($B39>=5,"P3 Maybe","P4 Low"))))))))))) | B39: 6.5 | C39: Mid-level | D39: Verification Engineer (f/m/d) | E39: Renesas Electronics | F39: Edinburgh, Scotland, UK | I39: =IF($H39="","",$H39-TODAY()) | J39: Open posting | K39: Verilog/FPGA ASIC verification role suits profile well; SystemVerilog/UVM gap exists but 2-5 years experience and graduate-level entry align well. | L39: new | N39: 5787a86335d01a78a4ce39707259868b05fb9d30 | O39: 46185 | P39: jobspy | Q39: Verilog, FPGA, Python, Git, digital design | R39: Verification Engineer FPGA Verilog digital | U39: 46193 | V39: v2-cv-accuracy-13b988b18da8ea7d
A40: =IF($L40="applied","Applied",IF($L40="interview","Interview",IF($L40="offer","Offer",IF($L40="rejected","Rejected",IF($L40="ignore","Ignore",IF($L40="archive","Archive",IF($L40="closed","Closed",IF($B40="","Unscored",IF(AND($B40>=8,OR($H40="",$H40-TODAY()<=14)),"P1 Apply",IF($B40>=7,"P2 Strong",IF($B40>=5,"P3 Maybe","P4 Low"))))))))))) | B40: 6.5 | C40: Unspecified | D40: Software Engineer | E40: GlobalLogic | F40: London Area, United Kingdom | I40: =IF($H40="","",$H40-TODAY()) | J40: Open posting | K40: Python, JavaScript, and REST APIs match core skills; role leans toward workflow automation and operations engineering, slightly off target but technically relevant. | L40: new | N40: 22cf1dd318a8ee52173e705cd10025b10315ad6c | O40: 46174 | P40: jobspy | Q40: Python, JavaScript, REST APIs, Git | R40: Junior Python Developer | U40: 46192 | V40: v2-cv-accuracy-13b988b18da8ea7d
A41: =IF($L41="applied","Applied",IF($L41="interview","Interview",IF($L41="offer","Offer",IF($L41="rejected","Rejected",IF($L41="ignore","Ignore",IF($L41="archive","Archive",IF($L41="closed","Closed",IF($B41="","Unscored",IF(AND($B41>=8,OR($H41="",$H41-TODAY()<=14)),"P1 Apply",IF($B41>=7,"P2 Strong",IF($B41>=5,"P3 Maybe","P4 Low"))))))))))) | B41: 6.5 | C41: Unspecified | D41: Python / Django Developer | E41: Bright Purple | F41: Edinburgh, Scotland, UK | I41: =IF($H41="","",$H41-TODAY()) | J41: Open posting | K41: Python, Django, REST APIs, JavaScript match core skills; remote role above salary floor; JD is vague on seniority but implies more than 2 years. | L41: new | N41: e9f1e76d6840bf343c7cfbe370f7d4ccb01b627d | P41: jobspy | Q41: Python, Django, REST APIs, JavaScript, Git | R41: Junior Python Developer remote | U41: 46192 | V41: v2-cv-accuracy-13b988b18da8ea7d
A42: =IF($L42="applied","Applied",IF($L42="interview","Interview",IF($L42="offer","Offer",IF($L42="rejected","Rejected",IF($L42="ignore","Ignore",IF($L42="archive","Archive",IF($L42="closed","Closed",IF($B42="","Unscored",IF(AND($B42>=8,OR($H42="",$H42-TODAY()<=14)),"P1 Apply",IF($B42>=7,"P2 Strong",IF($B42>=5,"P3 Maybe","P4 Low"))))))))))) | B42: 6.5 | C42: Unspecified | D42: Software Developer, Risk and Regulatory | E42: bet365 | F42: Stoke-On-Trent, England, UK | I42: =IF($H42="","",$H42-TODAY()) | J42: Open posting | K42: JavaScript and SQL match; Golang is a hard requirement not in profile, and Typescript only adjacent; full-stack focus partially fits. | L42: new | N42: 13273956279b754cdc860371b472255926d98f29 | P42: jobspy | Q42: JavaScript, SQL, React, Linux, Agile | R42: graduate Full Stack Developer | U42: 46192 | V42: v2-cv-accuracy-13b988b18da8ea7d
A43: =IF($L43="applied","Applied",IF($L43="interview","Interview",IF($L43="offer","Offer",IF($L43="rejected","Rejected",IF($L43="ignore","Ignore",IF($L43="archive","Archive",IF($L43="closed","Closed",IF($B43="","Unscored",IF(AND($B43>=8,OR($H43="",$H43-TODAY()<=14)),"P1 Apply",IF($B43>=7,"P2 Strong",IF($B43>=5,"P3 Maybe","P4 Low"))))))))))) | B43: 6.5 | C43: Senior/Lead | D43: Embedded Digital Design Engineer | E43: MBDA | F43: Stevenage, England, UK | I43: =IF($H43="","",$H43-TODAY()) | J43: Open posting | K43: FPGA, Verilog, Vivado, DSP, and embedded systems directly match core skills; salary ~£50-60k is above floor but role may expect more experience than 2 years. | L43: new | N43: 04114849b6056cbc526a993d041db9e0cf911b97 | O43: 46177 | P43: jobspy | Q43: FPGA, Verilog, Vivado, embedded systems, DSP | R43: Junior Hardware Engineer embedded digital design UK | U43: 46192 | V43: v2-cv-accuracy-13b988b18da8ea7d
A44: =IF($L44="applied","Applied",IF($L44="interview","Interview",IF($L44="offer","Offer",IF($L44="rejected","Rejected",IF($L44="ignore","Ignore",IF($L44="archive","Archive",IF($L44="closed","Closed",IF($B44="","Unscored",IF(AND($B44>=8,OR($H44="",$H44-TODAY()<=14)),"P1 Apply",IF($B44>=7,"P2 Strong",IF($B44>=5,"P3 Maybe","P4 Low"))))))))))) | B44: 6.5 | C44: Graduate/Entry | D44: Graduate Platform Engineer | E44: Lean Tree | F44: London Area, United Kingdom | I44: =IF($H44="","",$H44-TODAY()) | J44: Open posting | K44: Graduate platform/cloud role matches level and some skills (Docker, Kubernetes, CI/CD, Git) but cloud infrastructure and IaC experience are absent from profile. | L44: new | N44: f48697877b5a0b3d7ebb77639619f9e6e0a7e519 | O44: 46170 | P44: jobspy | Q44: Docker, Kubernetes, Git, CI/CD, Python | R44: Graduate DevOps Engineer Docker Kubernetes Python | U44: 46192 | V44: v2-cv-accuracy-13b988b18da8ea7d
A45: =IF($L45="applied","Applied",IF($L45="interview","Interview",IF($L45="offer","Offer",IF($L45="rejected","Rejected",IF($L45="ignore","Ignore",IF($L45="archive","Archive",IF($L45="closed","Closed",IF($B45="","Unscored",IF(AND($B45>=8,OR($H45="",$H45-TODAY()<=14)),"P1 Apply",IF($B45>=7,"P2 Strong",IF($B45>=5,"P3 Maybe","P4 Low"))))))))))) | B45: 6.2 | C45: Unspecified | D45: Software Engineer | E45: SRG | F45: Sedgefield, England, UK | I45: =IF($H45="","",$H45-TODAY()) | J45: Open posting | K45: Python, React, Node.js, sensor/hardware integration align well, but role is Sedgefield (outside 60mi radius) and salary above floor; AI/ML gaps minor. | L45: new | N45: 021546f4b2a5689f8452010b141d19155033ed6d | O45: 46183 | P45: jobspy | Q45: Python, React, Node.js, sensor integration, embedded systems | R45: Firmware Engineer Raspberry Pi embedded | U45: 46192 | V45: v2-cv-accuracy-13b988b18da8ea7d
A46: =IF($L46="applied","Applied",IF($L46="interview","Interview",IF($L46="offer","Offer",IF($L46="rejected","Rejected",IF($L46="ignore","Ignore",IF($L46="archive","Archive",IF($L46="closed","Closed",IF($B46="","Unscored",IF(AND($B46>=8,OR($H46="",$H46-TODAY()<=14)),"P1 Apply",IF($B46>=7,"P2 Strong",IF($B46>=5,"P3 Maybe","P4 Low"))))))))))) | B46: 6 | C46: Junior | D46: Junior Engineer | E46: Whitespace | F46: Belfast, Northern Ireland, UK | I46: =IF($H46="","",$H46-TODAY()) | J46: Open posting | K46: Python, Docker, Kubernetes, REST APIs, and Node.js all match, but Belfast location exceeds 60-mile radius and role is primarily software-focused. | L46: new | N46: 7de041b147b0c8f278336cebb729dad0ca9b5bd9 | P46: jobspy | Q46: Python, Docker, Kubernetes, Node.js, REST APIs | R46: Graduate Backend Developer Python Docker Kubernetes | U46: 46196 | V46: v2-cv-accuracy-13b988b18da8ea7d
A47: =IF($L47="applied","Applied",IF($L47="interview","Interview",IF($L47="offer","Offer",IF($L47="rejected","Rejected",IF($L47="ignore","Ignore",IF($L47="archive","Archive",IF($L47="closed","Closed",IF($B47="","Unscored",IF(AND($B47>=8,OR($H47="",$H47-TODAY()<=14)),"P1 Apply",IF($B47>=7,"P2 Strong",IF($B47>=5,"P3 Maybe","P4 Low"))))))))))) | B47: 6 | C47: Mid-level | D47: Public Cloud Assistant Infrastructure Engineer | E47: Lloyds Banking Group | F47: Bristol, England, UK | I47: =IF($H47="","",$H47-TODAY()) | J47: Open posting | K47: Kubernetes, Docker, Python, and CI/CD match; lacks Azure/GCP/Terraform experience and role is cloud-infrastructure focused rather than embedded/hardware. | L47: new | N47: c3573bae982a6ac992589305fa245959f22a08de | O47: 46184 | P47: jobspy | Q47: Kubernetes, Docker, Python, CI/CD, API integration | R47: Platform Engineer graduate Docker Kubernetes Git | U47: 46194 | V47: v2-cv-accuracy-13b988b18da8ea7d
A48: =IF($L48="applied","Applied",IF($L48="interview","Interview",IF($L48="offer","Offer",IF($L48="rejected","Rejected",IF($L48="ignore","Ignore",IF($L48="archive","Archive",IF($L48="closed","Closed",IF($B48="","Unscored",IF(AND($B48>=8,OR($H48="",$H48-TODAY()<=14)),"P1 Apply",IF($B48>=7,"P2 Strong",IF($B48>=5,"P3 Maybe","P4 Low"))))))))))) | B48: 6 | C48: Unspecified | D48: Software Engineer - Birkenhead | E48: Crowder Consulting | F48: Birkenhead, ENG, GB | I48: =IF($H48="","",$H48-TODAY()) | J48: Open posting | K48: Python, MySQL, Docker, APIs and CI/CD match well; Birkenhead location is ~70 miles from Sheffield, slightly outside search radius with hybrid working. | L48: new | N48: 97a37e8d5532300b5982e90ab78f83ac7ba8e4c3 | O48: 46183 | P48: jobspy | Q48: Python, MySQL, Docker, API integration, JavaScript | R48: Graduate Software Engineer Python Docker | U48: 46193 | V48: v2-cv-accuracy-13b988b18da8ea7d
A49: =IF($L49="applied","Applied",IF($L49="interview","Interview",IF($L49="offer","Offer",IF($L49="rejected","Rejected",IF($L49="ignore","Ignore",IF($L49="archive","Archive",IF($L49="closed","Closed",IF($B49="","Unscored",IF(AND($B49>=8,OR($H49="",$H49-TODAY()<=14)),"P1 Apply",IF($B49>=7,"P2 Strong",IF($B49>=5,"P3 Maybe","P4 Low"))))))))))) | B49: 6 | C49: Mid-level | D49: Public Cloud Assistant Infrastructure Engineer | E49: Lloyds Banking Group | F49: Leeds, England, UK | I49: =IF($H49="","",$H49-TODAY()) | J49: Open posting | K49: Kubernetes, Docker, Python, and CI/CD adjacent skills match this assistant-level cloud role; Terraform and Azure-specific experience are gaps but role suits a junior. | L49: new | N49: 899ac74c5d9863d95f709d93dbedc72db0bdb9c4 | O49: 46184 | P49: jobspy | Q49: Docker, Kubernetes, Python, CI/CD, API integration | R49: Graduate Computer Engineer Sheffield | U49: 46193 | V49: v2-cv-accuracy-13b988b18da8ea7d
A50: =IF($L50="applied","Applied",IF($L50="interview","Interview",IF($L50="offer","Offer",IF($L50="rejected","Rejected",IF($L50="ignore","Ignore",IF($L50="archive","Archive",IF($L50="closed","Closed",IF($B50="","Unscored",IF(AND($B50>=8,OR($H50="",$H50-TODAY()<=14)),"P1 Apply",IF($B50>=7,"P2 Strong",IF($B50>=5,"P3 Maybe","P4 Low"))))))))))) | B50: 6 | C50: Graduate/Entry | D50: Graduate Software Engineer | E50: targetjobs UK | F50: Gloucester, England, UK | I50: =IF($H50="","",$H50-TODAY()) | J50: Open posting | K50: Graduate SE role matches level and Python/JS/SQL skills, but Gloucester location exceeds 60-mile radius and defence context may require clearance. | L50: new | N50: 6f837dcdbfc2a939261956a535b2913948fce8d3 | P50: jobspy | Q50: Python, JavaScript, Agile, Git, PostgreSQL | R50: graduate Graduate Software Developer | U50: 46192 | V50: v2-cv-accuracy-13b988b18da8ea7d
A51: =IF($L51="applied","Applied",IF($L51="interview","Interview",IF($L51="offer","Offer",IF($L51="rejected","Rejected",IF($L51="ignore","Ignore",IF($L51="archive","Archive",IF($L51="closed","Closed",IF($B51="","Unscored",IF(AND($B51>=8,OR($H51="",$H51-TODAY()<=14)),"P1 Apply",IF($B51>=7,"P2 Strong",IF($B51>=5,"P3 Maybe","P4 Low"))))))))))) | B51: 5.8 | C51: Junior | D51: Associate Engineer | E51: IBM | F51: Hursley, England, UK | I51: =IF($H51="","",$H51-TODAY()) | J51: Open posting | K51: Graduate Associate Engineer role matches level; Systems/DevOps tracks align, but locations (Gloucester/London/Winchester) are outside 60-mile radius. | L51: new | N51: 01826141460a1e232e8ba410d4c473170b9cbf2c | O51: 46196 | P51: jobspy | Q51: Python, Docker, Kubernetes, CI/CD, API integration | R51: Graduate Software Engineer Python Docker Kubernetes | U51: 46197 | V51: v2-cv-accuracy-13b988b18da8ea7d
A52: =IF($L52="applied","Applied",IF($L52="interview","Interview",IF($L52="offer","Offer",IF($L52="rejected","Rejected",IF($L52="ignore","Ignore",IF($L52="archive","Archive",IF($L52="closed","Closed",IF($B52="","Unscored",IF(AND($B52>=8,OR($H52="",$H52-TODAY()<=14)),"P1 Apply",IF($B52>=7,"P2 Strong",IF($B52>=5,"P3 Maybe","P4 Low"))))))))))) | B52: 5.5 | C52: Junior | D52: Junior Software Engineer | E52: MCS Group | Your Specialist Recruitment Consultancy | F52: Belfast, Northern Ireland, UK | I52: =IF($H52="","",$H52-TODAY()) | J52: Open posting | K52: Python, Docker, Kubernetes match but requires 1-3 years commercial experience; Belfast is outside 60-mile radius and no PostgreSQL/MongoDB evidence. | L52: new | N52: 894b302b7ab4c0eebe10384e7c8b9a131dfeb8f5 | P52: jobspy | Q52: Python, Docker, Kubernetes, Git, REST APIs | R52: Junior Backend Developer Python Docker Kubernetes | U52: 46199 | V52: v2-cv-accuracy-13b988b18da8ea7d
A53: =IF($L53="applied","Applied",IF($L53="interview","Interview",IF($L53="offer","Offer",IF($L53="rejected","Rejected",IF($L53="ignore","Ignore",IF($L53="archive","Archive",IF($L53="closed","Closed",IF($B53="","Unscored",IF(AND($B53>=8,OR($H53="",$H53-TODAY()<=14)),"P1 Apply",IF($B53>=7,"P2 Strong",IF($B53>=5,"P3 Maybe","P4 Low"))))))))))) | B53: 5.5 | C53: Unspecified | D53: Software Engineer | E53: Spait Infotech | I53: =IF($H53="","",$H53-TODAY()) | J53: Open posting | K53: Python, SQL, MySQL, Docker, Kubernetes, Git match well but 2+ years exp requirement and vague JD reduce confidence; no hardware focus. | L53: new | N53: d716217771915ee6ecc9a6884678ad87860beb7e | O53: 46196 | P53: jobspy | Q53: Python, SQL, MySQL, Docker, Git | R53: Graduate Software Engineer Python SQL API | U53: 46199 | V53: v2-cv-accuracy-13b988b18da8ea7d
A54: =IF($L54="applied","Applied",IF($L54="interview","Interview",IF($L54="offer","Offer",IF($L54="rejected","Rejected",IF($L54="ignore","Ignore",IF($L54="archive","Archive",IF($L54="closed","Closed",IF($B54="","Unscored",IF(AND($B54>=8,OR($H54="",$H54-TODAY()<=14)),"P1 Apply",IF($B54>=7,"P2 Strong",IF($B54>=5,"P3 Maybe","P4 Low"))))))))))) | B54: 5.5 | C54: Unspecified | D54: Full Stack Software Engineer | E54: Frontier Resourcing | F54: Farnborough, England, UK | I54: =IF($H54="","",$H54-TODAY()) | J54: Open posting | K54: Python, Docker, Kubernetes, and Git match well; role is primarily fullstack software with Java/Go focus, hardware background underutilised. | L54: new | N54: ffb51a55628a61704a0254eabb62bd96f7abedcb | O54: 46193 | P54: jobspy | Q54: Python, Docker, Kubernetes, Git, JavaScript | R54: Junior Python Developer backend Docker Kubernetes | U54: 46196 | V54: v2-cv-accuracy-13b988b18da8ea7d
A55: =IF($L55="applied","Applied",IF($L55="interview","Interview",IF($L55="offer","Offer",IF($L55="rejected","Rejected",IF($L55="ignore","Ignore",IF($L55="archive","Archive",IF($L55="closed","Closed",IF($B55="","Unscored",IF(AND($B55>=8,OR($H55="",$H55-TODAY()<=14)),"P1 Apply",IF($B55>=7,"P2 Strong",IF($B55>=5,"P3 Maybe","P4 Low"))))))))))) | B55: 5.5 | C55: Mid-level | D55: Software Engineer | E55: JOBEE RECRUITMENT LTD | F55: London, ENG, GB | I55: =IF($H55="","",$H55-TODAY()) | J55: Open posting | K55: Python, SQL, Git, Linux, and API skills match well, but location is London on-site and JD is vague on seniority with a wide salary band. | L55: new | N55: 53a20bd306efb8795df98b3f8d6cf1e3f7269bfd | O55: 46175 | P55: jobspy | Q55: Python, SQL, MySQL, Git, API integration | R55: Graduate Software Engineer Python JavaScript remote | U55: 46196 | V55: v2-cv-accuracy-13b988b18da8ea7d
A56: =IF($L56="applied","Applied",IF($L56="interview","Interview",IF($L56="offer","Offer",IF($L56="rejected","Rejected",IF($L56="ignore","Ignore",IF($L56="archive","Archive",IF($L56="closed","Closed",IF($B56="","Unscored",IF(AND($B56>=8,OR($H56="",$H56-TODAY()<=14)),"P1 Apply",IF($B56>=7,"P2 Strong",IF($B56>=5,"P3 Maybe","P4 Low"))))))))))) | B56: 5.5 | C56: Junior | D56: Associate Engineer | E56: IBM | F56: Cheltenham, England, UK | I56: =IF($H56="","",$H56-TODAY()) | J56: Open posting | K56: Graduate Associate Engineer role matches seniority; but focus is government cloud/software consulting far from hardware/embedded core skills, locations outside 60-mile radius. | L56: new | N56: cdf357d0c45e5d898aa274bbc01b8095ee89ec7c | P56: jobspy | Q56: Docker, Kubernetes, CI/CD, backend development, Git | R56: Graduate Software Engineer Python Docker Kubernetes | U56: 46196 | V56: v2-cv-accuracy-13b988b18da8ea7d
A57: =IF($L57="applied","Applied",IF($L57="interview","Interview",IF($L57="offer","Offer",IF($L57="rejected","Rejected",IF($L57="ignore","Ignore",IF($L57="archive","Archive",IF($L57="closed","Closed",IF($B57="","Unscored",IF(AND($B57>=8,OR($H57="",$H57-TODAY()<=14)),"P1 Apply",IF($B57>=7,"P2 Strong",IF($B57>=5,"P3 Maybe","P4 Low"))))))))))) | B57: 5.5 | C57: Unspecified | D57: Digital Signal Processing DSP Engineer | E57: Lockheed Martin | F57: Gloucester, England, UK | I57: =IF($H57="","",$H57-TODAY()) | J57: Open posting | K57: DSP and signal processing skills align, but role requires RF/SDR reverse engineering experience absent from profile; Gloucester location is outside 60-mile radius. | L57: new | N57: c3cbea0593f8cfedd9b79713be21af12a5d44922 | O57: 46175 | P57: jobspy | Q57: DSP, Python, C, signal processing, digital design | R57: Graduate Signal Processing Engineer DSP | U57: 46193 | V57: v2-cv-accuracy-13b988b18da8ea7d
A58: =IF($L58="applied","Applied",IF($L58="interview","Interview",IF($L58="offer","Offer",IF($L58="rejected","Rejected",IF($L58="ignore","Ignore",IF($L58="archive","Archive",IF($L58="closed","Closed",IF($B58="","Unscored",IF(AND($B58>=8,OR($H58="",$H58-TODAY()<=14)),"P1 Apply",IF($B58>=7,"P2 Strong",IF($B58>=5,"P3 Maybe","P4 Low"))))))))))) | B58: 5.5 | C58: Unspecified | D58: Field-Programmable Gate Arrays Engineer | E58: AAA Global | F58: England, United Kingdom | I58: =IF($H58="","",$H58-TODAY()) | J58: Open posting | K58: FPGA dissertation and Verilog are directly relevant, but role requires professional FPGA/ASIC experience and C++, which the profile lacks. | L58: new | N58: 1d66456f6a8ff61c8aaaa086e50cb68c8646cc0c | O58: 46185 | P58: jobspy | Q58: FPGA, Verilog, Vivado, digital design, Python | R58: Hardware Engineer graduate FPGA digital design | U58: 46193 | V58: v2-cv-accuracy-13b988b18da8ea7d
A59: =IF($L59="applied","Applied",IF($L59="interview","Interview",IF($L59="offer","Offer",IF($L59="rejected","Rejected",IF($L59="ignore","Ignore",IF($L59="archive","Archive",IF($L59="closed","Closed",IF($B59="","Unscored",IF(AND($B59>=8,OR($H59="",$H59-TODAY()<=14)),"P1 Apply",IF($B59>=7,"P2 Strong",IF($B59>=5,"P3 Maybe","P4 Low"))))))))))) | B59: 5.5 | C59: Unspecified | D59: Software Engineer (Yocto / Buildroot) – Next-Generation Space Tech | E59: GTS Group Ltd | F59: Loughborough, England, UK | I59: =IF($H59="","",$H59-TODAY()) | J59: Open posting | K59: IoT and embedded systems overlap, but Yocto/Buildroot and bootloader dev are missing from profile; on-site Loughborough may exceed 60-mile radius. | L59: new | N59: 36fc034bb9c49f538199e3290b6484188c50243d | O59: 46174 | P59: jobspy | Q59: IoT, STM32, Python, embedded systems, LoRaWAN | R59: Firmware Engineer Embedded C Microcontroller | U59: 46193 | V59: v2-cv-accuracy-13b988b18da8ea7d
A60: =IF($L60="applied","Applied",IF($L60="interview","Interview",IF($L60="offer","Offer",IF($L60="rejected","Rejected",IF($L60="ignore","Ignore",IF($L60="archive","Archive",IF($L60="closed","Closed",IF($B60="","Unscored",IF(AND($B60>=8,OR($H60="",$H60-TODAY()<=14)),"P1 Apply",IF($B60>=7,"P2 Strong",IF($B60>=5,"P3 Maybe","P4 Low"))))))))))) | B60: 5.5 | C60: Unspecified | D60: Embedded Software Engineer (LDN) | E60: Cirrus Logic | F60: London, England, UK | I60: =IF($H60="","",$H60-TODAY()) | J60: Open posting | K60: Strong embedded/DSP/FPGA alignment but role requires professional C/C++ MCU firmware experience beyond candidate's academic level. | L60: new | N60: 864164eb4888b72b85c23bec7ce000d613957a63 | O60: 46187 | P60: jobspy | Q60: embedded systems, DSP, FPGA, C, digital design | R60: Embedded Systems Engineer FPGA DSP | U60: 46193 | V60: v2-cv-accuracy-13b988b18da8ea7d
A61: =IF($L61="applied","Applied",IF($L61="interview","Interview",IF($L61="offer","Offer",IF($L61="rejected","Rejected",IF($L61="ignore","Ignore",IF($L61="archive","Archive",IF($L61="closed","Closed",IF($B61="","Unscored",IF(AND($B61>=8,OR($H61="",$H61-TODAY()<=14)),"P1 Apply",IF($B61>=7,"P2 Strong",IF($B61>=5,"P3 Maybe","P4 Low"))))))))))) | B61: 5.5 | C61: Unspecified | D61: Embedded Software Engineer (NWB) | E61: Cirrus Logic | F61: London, England, UK | I61: =IF($H61="","",$H61-TODAY()) | J61: Open posting | K61: Same strong embedded alignment as LDN role but location unclear; same gap in professional C/C++ MCU firmware depth. | L61: new | N61: 0b191a5177b6fdce5edb0fe0125d6842582176d6 | O61: 46186 | P61: jobspy | Q61: embedded systems, DSP, FPGA, C, digital design | R61: Embedded Systems Engineer FPGA DSP | U61: 46193 | V61: v2-cv-accuracy-13b988b18da8ea7d
A62: =IF($L62="applied","Applied",IF($L62="interview","Interview",IF($L62="offer","Offer",IF($L62="rejected","Rejected",IF($L62="ignore","Ignore",IF($L62="archive","Archive",IF($L62="closed","Closed",IF($B62="","Unscored",IF(AND($B62>=8,OR($H62="",$H62-TODAY()<=14)),"P1 Apply",IF($B62>=7,"P2 Strong",IF($B62>=5,"P3 Maybe","P4 Low"))))))))))) | B62: 5.5 | C62: Unspecified | D62: Software Developer, Risk and Regulatory | E62: bet365 | F62: Manchester, England, UK | I62: =IF($H62="","",$H62-TODAY()) | J62: Open posting | K62: JavaScript and SQL match but core stack requires Golang and TypeScript which are not in candidate's core skills; Stoke location unclear. | L62: new | N62: bbea7bd22439c0bc3828a489345a5dcabd3ff61b | P62: jobspy | Q62: JavaScript, SQL, Agile, REST APIs | R62: Full Stack Developer | U62: 46192 | V62: v2-cv-accuracy-13b988b18da8ea7d
A63: =IF($L63="applied","Applied",IF($L63="interview","Interview",IF($L63="offer","Offer",IF($L63="rejected","Rejected",IF($L63="ignore","Ignore",IF($L63="archive","Archive",IF($L63="closed","Closed",IF($B63="","Unscored",IF(AND($B63>=8,OR($H63="",$H63-TODAY()<=14)),"P1 Apply",IF($B63>=7,"P2 Strong",IF($B63>=5,"P3 Maybe","P4 Low"))))))))))) | B63: 5.5 | C63: Senior/Lead | D63: Data Engineer | E63: Fasanara Capital | F63: London, England, UK | I63: =IF($H63="","",$H63-TODAY()) | J63: Open posting | K63: Python and SQL/data pipeline skills match, but role targets crypto fintech with real-time low-latency trading systems beyond candidate's experience level. | L63: new | N63: b2f150dae5218a0d0347341c053ad35bc38f8958 | O63: 46175 | P63: jobspy | Q63: Python, SQL, data pipelines, API integration, backend development | R63: Graduate Data Engineer SQL Python pipeline | U63: 46192 | V63: v2-cv-accuracy-13b988b18da8ea7d
A64: =IF($L64="applied","Applied",IF($L64="interview","Interview",IF($L64="offer","Offer",IF($L64="rejected","Rejected",IF($L64="ignore","Ignore",IF($L64="archive","Archive",IF($L64="closed","Closed",IF($B64="","Unscored",IF(AND($B64>=8,OR($H64="",$H64-TODAY()<=14)),"P1 Apply",IF($B64>=7,"P2 Strong",IF($B64>=5,"P3 Maybe","P4 Low"))))))))))) | B64: 5.5 | C64: Unspecified | D64: Data Engineer | E64: Investigo | F64: Birmingham, England, UK | I64: =IF($H64="","",$H64-TODAY()) | J64: Open posting | K64: SQL, Python, Docker, API integration match well, but role expects cloud data warehouse and Airflow experience not evidenced in the profile. | L64: new | N64: 209242566c1938717eed2a3d254c0abb85aa200a | O64: 46181 | P64: jobspy | Q64: Python, SQL, Docker, API integration, Git | R64: Graduate Data Engineer SQL Python pipeline | U64: 46192 | V64: v2-cv-accuracy-13b988b18da8ea7d
A65: =IF($L65="applied","Applied",IF($L65="interview","Interview",IF($L65="offer","Offer",IF($L65="rejected","Rejected",IF($L65="ignore","Ignore",IF($L65="archive","Archive",IF($L65="closed","Closed",IF($B65="","Unscored",IF(AND($B65>=8,OR($H65="",$H65-TODAY()<=14)),"P1 Apply",IF($B65>=7,"P2 Strong",IF($B65>=5,"P3 Maybe","P4 Low"))))))))))) | B65: 5.5 | C65: Unspecified | D65: Validation Engineer | E65: Cirrus Logic | F65: Edinburgh, Scotland, UK | I65: =IF($H65="","",$H65-TODAY()) | J65: Open posting | K65: Electronics degree and Python/hardware skills align, but role needs analog/mixed-signal validation and PCB design experience not evidenced in profile. | L65: new | N65: 2746feee3ae53f62b800611973c920e0eeace21b | O65: 46170 | P65: jobspy | Q65: Python, FPGA, digital design, embedded systems, hardware design | R65: Graduate Verification Engineer Verilog digital | U65: 46192 | V65: v2-cv-accuracy-13b988b18da8ea7d
A66: =IF($L66="applied","Applied",IF($L66="interview","Interview",IF($L66="offer","Offer",IF($L66="rejected","Rejected",IF($L66="ignore","Ignore",IF($L66="archive","Archive",IF($L66="closed","Closed",IF($B66="","Unscored",IF(AND($B66>=8,OR($H66="",$H66-TODAY()<=14)),"P1 Apply",IF($B66>=7,"P2 Strong",IF($B66>=5,"P3 Maybe","P4 Low"))))))))))) | B66: 5.5 | C66: Senior/Lead | D66: DevOps Engineer | E66: Next | F66: Leicester, England, UK | I66: =IF($H66="","",$H66-TODAY()) | J66: Open posting | K66: Docker, Kubernetes, Git, and CI/CD are present in profile; role lacks hardware focus and JD detail on seniority/salary is thin. | L66: new | N66: e061a7e5945e808fce2c5563a4fcb6363cb92762 | O66: 46188 | P66: jobspy | Q66: Docker, Kubernetes, Git, CI/CD, Python | R66: Graduate DevOps Engineer Docker Kubernetes Git | U66: 46192 | V66: v2-cv-accuracy-13b988b18da8ea7d
A67: =IF($L67="applied","Applied",IF($L67="interview","Interview",IF($L67="offer","Offer",IF($L67="rejected","Rejected",IF($L67="ignore","Ignore",IF($L67="archive","Archive",IF($L67="closed","Closed",IF($B67="","Unscored",IF(AND($B67>=8,OR($H67="",$H67-TODAY()<=14)),"P1 Apply",IF($B67>=7,"P2 Strong",IF($B67>=5,"P3 Maybe","P4 Low"))))))))))) | B67: 5.5 | C67: Unspecified | D67: DevOps Engineer | E67: CGI | F67: Gloucester, England, UK | I67: =IF($H67="","",$H67-TODAY()) | J67: Open posting | K67: Docker/Kubernetes and Python match, but role needs strong DevOps experience, is Gloucester on-site only, and likely needs SC clearance. | L67: new | N67: c2544d95879d9c0cea3bd590575b0e121b87b9c0 | O67: 46173 | P67: jobspy | Q67: Docker, Kubernetes, Python, MySQL, Git | R67: Graduate DevOps Engineer Docker Kubernetes Git | U67: 46192 | V67: v2-cv-accuracy-13b988b18da8ea7d
A68: =IF($L68="applied","Applied",IF($L68="interview","Interview",IF($L68="offer","Offer",IF($L68="rejected","Rejected",IF($L68="ignore","Ignore",IF($L68="archive","Archive",IF($L68="closed","Closed",IF($B68="","Unscored",IF(AND($B68>=8,OR($H68="",$H68-TODAY()<=14)),"P1 Apply",IF($B68>=7,"P2 Strong",IF($B68>=5,"P3 Maybe","P4 Low"))))))))))) | B68: 5.2 | C68: Mid-level | D68: Full-Stack Developer | E68: Intec Select | F68: London Area, United Kingdom | I68: =IF($H68="","",$H68-TODAY()) | J68: Open posting | K68: React, Node.js, SQL, Git match adjacent skills, but TypeScript is absent from profile and role is London-based with no salary stated. | L68: new | N68: 5405a5d5c62ae4fee126e91fbd86164a62cb2367 | O68: 46177 | P68: jobspy | Q68: React, Node.js, SQL, Git, Docker | R68: Junior Python Developer backend SQL Docker | U68: 46196 | V68: v2-cv-accuracy-13b988b18da8ea7d
A69: =IF($L69="applied","Applied",IF($L69="interview","Interview",IF($L69="offer","Offer",IF($L69="rejected","Rejected",IF($L69="ignore","Ignore",IF($L69="archive","Archive",IF($L69="closed","Closed",IF($B69="","Unscored",IF(AND($B69>=8,OR($H69="",$H69-TODAY()<=14)),"P1 Apply",IF($B69>=7,"P2 Strong",IF($B69>=5,"P3 Maybe","P4 Low"))))))))))) | B69: 5.2 | C69: Mid-level | D69: Back End Developer | E69: Spotted Recruitment | F69: Manchester, England, UK | I69: =IF($H69="","",$H69-TODAY()) | J69: Open posting | K69: SQL and backend/API skills match well but role requires commercial backend experience and Manchester office attendance weekly, location borderline. | L69: new | N69: d624f3981eeac0e5726df90b0fc9001a22a10a74 | O69: 46181 | P69: jobspy | Q69: SQL, MySQL, API integration, Python, Git | R69: Junior Python Developer backend SQL Sheffield | U69: 46193 | V69: v2-cv-accuracy-13b988b18da8ea7d
A70: =IF($L70="applied","Applied",IF($L70="interview","Interview",IF($L70="offer","Offer",IF($L70="rejected","Rejected",IF($L70="ignore","Ignore",IF($L70="archive","Archive",IF($L70="closed","Closed",IF($B70="","Unscored",IF(AND($B70>=8,OR($H70="",$H70-TODAY()<=14)),"P1 Apply",IF($B70>=7,"P2 Strong",IF($B70>=5,"P3 Maybe","P4 Low"))))))))))) | B70: 5.2 | C70: Senior/Lead | D70: Data & ML Platform Engineer | E70: TEKEVER | F70: Greater Bristol Area, United Kingdom | I70: =IF($H70="","",$H70-TODAY()) | J70: Open posting | K70: SQL, Docker, Kubernetes, and API integration match, but role requires MLOps/data science background and cloud platform experience absent from profile. | L70: new | N70: 860bf314a5c820450850c1a72e588a4fb721873f | O70: 46185 | P70: jobspy | Q70: SQL, Docker, Kubernetes, API integration, Python | R70: Graduate Data Engineer Python SQL MySQL | U70: 46193 | V70: v2-cv-accuracy-13b988b18da8ea7d
A71: =IF($L71="applied","Applied",IF($L71="interview","Interview",IF($L71="offer","Offer",IF($L71="rejected","Rejected",IF($L71="ignore","Ignore",IF($L71="archive","Archive",IF($L71="closed","Closed",IF($B71="","Unscored",IF(AND($B71>=8,OR($H71="",$H71-TODAY()<=14)),"P1 Apply",IF($B71>=7,"P2 Strong",IF($B71>=5,"P3 Maybe","P4 Low"))))))))))) | B71: 5 | C71: Unspecified | D71: Automation and Software Developer | E71: TipTopJob | F71: West Yorkshire, England, UK | I71: =IF($H71="","",$H71-TODAY()) | J71: Open posting | K71: API integration, Python, and backend skills match; Leeds office-based within range, but retail focus and AI-tooling emphasis are weak fits. | L71: new | N71: 6d645385990acd80f05aadf5e5e514dc1cd83924 | O71: 46183 | P71: jobspy | Q71: Python, API integration, MySQL, Docker, Git | R71: Graduate Software Engineer Python SQL API | U71: 46199 | V71: v2-cv-accuracy-13b988b18da8ea7d
A72: =IF($L72="applied","Applied",IF($L72="interview","Interview",IF($L72="offer","Offer",IF($L72="rejected","Rejected",IF($L72="ignore","Ignore",IF($L72="archive","Archive",IF($L72="closed","Closed",IF($B72="","Unscored",IF(AND($B72>=8,OR($H72="",$H72-TODAY()<=14)),"P1 Apply",IF($B72>=7,"P2 Strong",IF($B72>=5,"P3 Maybe","P4 Low"))))))))))) | B72: 5 | C72: Graduate/Entry | D72: Graduate Cloud and AI Engineer | E72: Reply | F72: Manchester Area, United Kingdom | I72: =IF($H72="","",$H72-TODAY()) | J72: Open posting | K72: Graduate cloud/AI role is level-appropriate and IoT/API skills match, but AWS-heavy focus and no evidence of AWS or frontend experience in profile. | L72: new | N72: 7537e762b73b86e2271ca923dca542ce22af351a | O72: 46196 | P72: jobspy | Q72: Python, IoT, API integration, Docker, backend development | R72: Graduate Software Engineer Python Docker Kubernetes | U72: 46197 | V72: v2-cv-accuracy-13b988b18da8ea7d
A73: =IF($L73="applied","Applied",IF($L73="interview","Interview",IF($L73="offer","Offer",IF($L73="rejected","Rejected",IF($L73="ignore","Ignore",IF($L73="archive","Archive",IF($L73="closed","Closed",IF($B73="","Unscored",IF(AND($B73>=8,OR($H73="",$H73-TODAY()<=14)),"P1 Apply",IF($B73>=7,"P2 Strong",IF($B73>=5,"P3 Maybe","P4 Low"))))))))))) | B73: 5 | C73: Unspecified | D73: Signal Processing Software Engineer | E73: SII Group UK | F73: Manchester, England, UK | I73: =IF($H73="","",$H73-TODAY()) | J73: Open posting | K73: Signal processing is adjacent but role requires strong C++ and Linux software engineering depth not evidenced in profile. | L73: new | N73: afcfb82e4c48bb51c551a4b576e6ec101b8e36a2 | O73: 46176 | P73: jobspy | Q73: signal processing, Git, Linux, C | R73: Signal Processing Engineer graduate DSP | U73: 46195 | V73: v2-cv-accuracy-13b988b18da8ea7d
A74: =IF($L74="applied","Applied",IF($L74="interview","Interview",IF($L74="offer","Offer",IF($L74="rejected","Rejected",IF($L74="ignore","Ignore",IF($L74="archive","Archive",IF($L74="closed","Closed",IF($B74="","Unscored",IF(AND($B74>=8,OR($H74="",$H74-TODAY()<=14)),"P1 Apply",IF($B74>=7,"P2 Strong",IF($B74>=5,"P3 Maybe","P4 Low"))))))))))) | B74: 5 | C74: Mid-level | D74: Software Engineer I | E74: RELX | F74: Cardiff, Wales, UK | I74: =IF($H74="","",$H74-TODAY()) | J74: Open posting | K74: PHP and Go are hard requirements absent from the profile; Python interest credited but core stack mismatch is significant. | L74: new | N74: 91b7f65840c7d67e2b79c8a305d73fe079a8d807 | O74: 46184 | P74: jobspy | Q74: Python, CI/CD, Agile, Git | R74: entry level Full Stack Developer | U74: 46192 | V74: v2-cv-accuracy-13b988b18da8ea7d
A75: =IF($L75="applied","Applied",IF($L75="interview","Interview",IF($L75="offer","Offer",IF($L75="rejected","Rejected",IF($L75="ignore","Ignore",IF($L75="archive","Archive",IF($L75="closed","Closed",IF($B75="","Unscored",IF(AND($B75>=8,OR($H75="",$H75-TODAY()<=14)),"P1 Apply",IF($B75>=7,"P2 Strong",IF($B75>=5,"P3 Maybe","P4 Low"))))))))))) | B75: 5 | C75: Unspecified | D75: Security Shift Officer | E75: Dyson | F75: United Kingdom - Malmesbury Office | I75: =IF($H75="","",$H75-TODAY()) | J75: Open posting | L75: new | N75: 7086bd3d2bb244a5ec739c047c5375c0790713ad | P75: workday | U75: 46190
A76: =IF($L76="applied","Applied",IF($L76="interview","Interview",IF($L76="offer","Offer",IF($L76="rejected","Rejected",IF($L76="ignore","Ignore",IF($L76="archive","Archive",IF($L76="closed","Closed",IF($B76="","Unscored",IF(AND($B76>=8,OR($H76="",$H76-TODAY()<=14)),"P1 Apply",IF($B76>=7,"P2 Strong",IF($B76>=5,"P3 Maybe","P4 Low"))))))))))) | B76: 5 | C76: Graduate/Entry | D76: Advanced New Product Development Graduate Engineer | E76: Dyson | F76: Malaysia - Global Development Campus, Johor Bahru | I76: =IF($H76="","",$H76-TODAY()) | J76: Open posting | L76: new | N76: beb74ed40776b5937ce915f3513ac0700cce6e4b | P76: workday | U76: 46190
A77: =IF($L77="applied","Applied",IF($L77="interview","Interview",IF($L77="offer","Offer",IF($L77="rejected","Rejected",IF($L77="ignore","Ignore",IF($L77="archive","Archive",IF($L77="closed","Closed",IF($B77="","Unscored",IF(AND($B77>=8,OR($H77="",$H77-TODAY()<=14)),"P1 Apply",IF($B77>=7,"P2 Strong",IF($B77>=5,"P3 Maybe","P4 Low"))))))))))) | B77: 5 | C77: Unspecified | D77: Retail Expert (CDD) | E77: Dyson | F77: France - Paris Opera Demo Store | I77: =IF($H77="","",$H77-TODAY()) | J77: Open posting | L77: new | N77: 329ac8c8fba466ae0e76c0feaadb235f527d90a4 | P77: workday | U77: 46190
A78: =IF($L78="applied","Applied",IF($L78="interview","Interview",IF($L78="offer","Offer",IF($L78="rejected","Rejected",IF($L78="ignore","Ignore",IF($L78="archive","Archive",IF($L78="closed","Closed",IF($B78="","Unscored",IF(AND($B78>=8,OR($H78="",$H78-TODAY()<=14)),"P1 Apply",IF($B78>=7,"P2 Strong",IF($B78>=5,"P3 Maybe","P4 Low"))))))))))) | B78: 5 | C78: Manager/Owner | D78: General Sales Manager | E78: Dyson | F78: India - Bangalore Sales Office | I78: =IF($H78="","",$H78-TODAY()) | J78: Open posting | L78: new | N78: dbe57fe2564478c04f8fc4963cf8a59fa5ed2ce9 | P78: workday | U78: 46190
A79: =IF($L79="applied","Applied",IF($L79="interview","Interview",IF($L79="offer","Offer",IF($L79="rejected","Rejected",IF($L79="ignore","Ignore",IF($L79="archive","Archive",IF($L79="closed","Closed",IF($B79="","Unscored",IF(AND($B79>=8,OR($H79="",$H79-TODAY()<=14)),"P1 Apply",IF($B79>=7,"P2 Strong",IF($B79>=5,"P3 Maybe","P4 Low"))))))))))) | B79: 5 | C79: Unspecified | D79: Retail Sales Assistant - Various Locations | E79: Dyson | F79: Australia - Victoria Remote | I79: =IF($H79="","",$H79-TODAY()) | J79: Open posting | L79: new | N79: 7d800bdd1ed7c1051307dd72af11ebde27e0b518 | P79: workday | U79: 46190
A80: =IF($L80="applied","Applied",IF($L80="interview","Interview",IF($L80="offer","Offer",IF($L80="rejected","Rejected",IF($L80="ignore","Ignore",IF($L80="archive","Archive",IF($L80="closed","Closed",IF($B80="","Unscored",IF(AND($B80>=8,OR($H80="",$H80-TODAY()<=14)),"P1 Apply",IF($B80>=7,"P2 Strong",IF($B80>=5,"P3 Maybe","P4 Low"))))))))))) | B80: 5 | C80: Manager/Owner | D80: Marketplaces Manager | E80: Dyson | F80: Netherlands - Amsterdam Office | I80: =IF($H80="","",$H80-TODAY()) | J80: Open posting | L80: new | N80: 62008e66bd3022ebaa97fbad1090a43197b0edbf | P80: workday | U80: 46190
A81: =IF($L81="applied","Applied",IF($L81="interview","Interview",IF($L81="offer","Offer",IF($L81="rejected","Rejected",IF($L81="ignore","Ignore",IF($L81="archive","Archive",IF($L81="closed","Closed",IF($B81="","Unscored",IF(AND($B81>=8,OR($H81="",$H81-TODAY()<=14)),"P1 Apply",IF($B81>=7,"P2 Strong",IF($B81>=5,"P3 Maybe","P4 Low"))))))))))) | B81: 5 | C81: Unspecified | D81: Trading Activation Executive (Parental Leave Cover) | E81: Dyson | F81: Sweden - Stockholm Office | I81: =IF($H81="","",$H81-TODAY()) | J81: Open posting | L81: new | N81: 239fac7818f94dd7509d0a00518e1333aaa8675f | P81: workday | U81: 46190
A82: =IF($L82="applied","Applied",IF($L82="interview","Interview",IF($L82="offer","Offer",IF($L82="rejected","Rejected",IF($L82="ignore","Ignore",IF($L82="archive","Archive",IF($L82="closed","Closed",IF($B82="","Unscored",IF(AND($B82>=8,OR($H82="",$H82-TODAY()<=14)),"P1 Apply",IF($B82>=7,"P2 Strong",IF($B82>=5,"P3 Maybe","P4 Low"))))))))))) | B82: 5 | C82: Graduate/Entry | D82: 2026 Graduate Firmware Engineer | E82: Graphcore | F82: Bristol, UK | I82: =IF($H82="","",$H82-TODAY()) | J82: Open posting | L82: new | N82: 31853c891a9612d645ea869eff2f79c20c7f21fb | O82: 46189 | P82: greenhouse:graphcore | U82: 46189
A83: =IF($L83="applied","Applied",IF($L83="interview","Interview",IF($L83="offer","Offer",IF($L83="rejected","Rejected",IF($L83="ignore","Ignore",IF($L83="archive","Archive",IF($L83="closed","Closed",IF($B83="","Unscored",IF(AND($B83>=8,OR($H83="",$H83-TODAY()<=14)),"P1 Apply",IF($B83>=7,"P2 Strong",IF($B83>=5,"P3 Maybe","P4 Low"))))))))))) | B83: 5 | C83: Graduate/Entry | D83: 2026 Graduate Software Engineer - Drivers | E83: Graphcore | F83: Bristol, UK | I83: =IF($H83="","",$H83-TODAY()) | J83: Open posting | L83: new | N83: 3c4944fca3dbd2cce7be68bba67e371029fa594f | O83: 46189 | P83: greenhouse:graphcore | U83: 46189
A84: =IF($L84="applied","Applied",IF($L84="interview","Interview",IF($L84="offer","Offer",IF($L84="rejected","Rejected",IF($L84="ignore","Ignore",IF($L84="archive","Archive",IF($L84="closed","Closed",IF($B84="","Unscored",IF(AND($B84>=8,OR($H84="",$H84-TODAY()<=14)),"P1 Apply",IF($B84>=7,"P2 Strong",IF($B84>=5,"P3 Maybe","P4 Low"))))))))))) | B84: 5 | C84: Graduate/Entry | D84: 2026 Graduate Software Engineer - Drivers | E84: Graphcore | F84: Cambridge, UK | I84: =IF($H84="","",$H84-TODAY()) | J84: Open posting | L84: new | N84: de00f232f0af706b5f23b86f2be58e61a979c7a4 | O84: 46189 | P84: greenhouse:graphcore | U84: 46189
A85: =IF($L85="applied","Applied",IF($L85="interview","Interview",IF($L85="offer","Offer",IF($L85="rejected","Rejected",IF($L85="ignore","Ignore",IF($L85="archive","Archive",IF($L85="closed","Closed",IF($B85="","Unscored",IF(AND($B85>=8,OR($H85="",$H85-TODAY()<=14)),"P1 Apply",IF($B85>=7,"P2 Strong",IF($B85>=5,"P3 Maybe","P4 Low"))))))))))) | B85: 5 | C85: Graduate/Entry | D85: 2026 Graduate Software Engineer - ML Kernels & Runtime Team | E85: Graphcore | F85: Bristol, UK | I85: =IF($H85="","",$H85-TODAY()) | J85: Open posting | L85: new | N85: 789877cef58d67f00a4c02378a1eed77aeab946c | O85: 46189 | P85: greenhouse:graphcore | U85: 46189
A86: =IF($L86="applied","Applied",IF($L86="interview","Interview",IF($L86="offer","Offer",IF($L86="rejected","Rejected",IF($L86="ignore","Ignore",IF($L86="archive","Archive",IF($L86="closed","Closed",IF($B86="","Unscored",IF(AND($B86>=8,OR($H86="",$H86-TODAY()<=14)),"P1 Apply",IF($B86>=7,"P2 Strong",IF($B86>=5,"P3 Maybe","P4 Low"))))))))))) | B86: 5 | C86: Graduate/Entry | D86: 2026 Graduate Software Engineer - PyTorch | E86: Graphcore | F86: Bristol, UK | I86: =IF($H86="","",$H86-TODAY()) | J86: Open posting | L86: new | N86: 4cb4bf5b936749248e8de6ec1e2c44e95e34b912 | O86: 46189 | P86: greenhouse:graphcore | U86: 46189
A87: =IF($L87="applied","Applied",IF($L87="interview","Interview",IF($L87="offer","Offer",IF($L87="rejected","Rejected",IF($L87="ignore","Ignore",IF($L87="archive","Archive",IF($L87="closed","Closed",IF($B87="","Unscored",IF(AND($B87>=8,OR($H87="",$H87-TODAY()<=14)),"P1 Apply",IF($B87>=7,"P2 Strong",IF($B87>=5,"P3 Maybe","P4 Low"))))))))))) | B87: 5 | C87: Graduate/Entry | D87: 2026 Graduate Software Engineer - Triton | E87: Graphcore | F87: Bristol, UK | I87: =IF($H87="","",$H87-TODAY()) | J87: Open posting | L87: new | N87: f3c6805fd358be96ae330699622fd5bb99a20d4e | O87: 46189 | P87: greenhouse:graphcore | U87: 46189
A88: =IF($L88="applied","Applied",IF($L88="interview","Interview",IF($L88="offer","Offer",IF($L88="rejected","Rejected",IF($L88="ignore","Ignore",IF($L88="archive","Archive",IF($L88="closed","Closed",IF($B88="","Unscored",IF(AND($B88>=8,OR($H88="",$H88-TODAY()<=14)),"P1 Apply",IF($B88>=7,"P2 Strong",IF($B88>=5,"P3 Maybe","P4 Low"))))))))))) | B88: 5 | C88: Unspecified | D88: AI Performance Engineer | E88: Graphcore | F88: US - Milpitas | I88: =IF($H88="","",$H88-TODAY()) | J88: Open posting | L88: new | N88: 692a5a8edd0d969ff9a4265353e2f00100f72fcc | O88: 46189 | P88: greenhouse:graphcore | U88: 46189
A89: =IF($L89="applied","Applied",IF($L89="interview","Interview",IF($L89="offer","Offer",IF($L89="rejected","Rejected",IF($L89="ignore","Ignore",IF($L89="archive","Archive",IF($L89="closed","Closed",IF($B89="","Unscored",IF(AND($B89>=8,OR($H89="",$H89-TODAY()<=14)),"P1 Apply",IF($B89>=7,"P2 Strong",IF($B89>=5,"P3 Maybe","P4 Low"))))))))))) | B89: 5 | C89: Senior/Lead | D89: AI Platform Architect | E89: Graphcore | F89: Austin, Texas, United States | I89: =IF($H89="","",$H89-TODAY()) | J89: Open posting | L89: new | N89: d4528279bfa348bb12136027b1e17006bccd5879 | O89: 46189 | P89: greenhouse:graphcore | U89: 46189
A90: =IF($L90="applied","Applied",IF($L90="interview","Interview",IF($L90="offer","Offer",IF($L90="rejected","Rejected",IF($L90="ignore","Ignore",IF($L90="archive","Archive",IF($L90="closed","Closed",IF($B90="","Unscored",IF(AND($B90>=8,OR($H90="",$H90-TODAY()<=14)),"P1 Apply",IF($B90>=7,"P2 Strong",IF($B90>=5,"P3 Maybe","P4 Low"))))))))))) | B90: 5 | C90: Unspecified | D90: AI Research Engineer | E90: Graphcore | F90: Bristol, UK; Cambridge, UK; London, UK | I90: =IF($H90="","",$H90-TODAY()) | J90: Open posting | L90: new | N90: a95bcd3a01b424802027196a78bb5225e972c2d6 | O90: 46189 | P90: greenhouse:graphcore | U90: 46189
A91: =IF($L91="applied","Applied",IF($L91="interview","Interview",IF($L91="offer","Offer",IF($L91="rejected","Rejected",IF($L91="ignore","Ignore",IF($L91="archive","Archive",IF($L91="closed","Closed",IF($B91="","Unscored",IF(AND($B91>=8,OR($H91="",$H91-TODAY()<=14)),"P1 Apply",IF($B91>=7,"P2 Strong",IF($B91>=5,"P3 Maybe","P4 Low"))))))))))) | B91: 5 | C91: Senior/Lead | D91: Atlassian Engineer | E91: Graphcore | F91: Bengaluru, India | I91: =IF($H91="","",$H91-TODAY()) | J91: Open posting | L91: new | N91: 7a9950437a23ff2a7512dc76539a24f9f8372863 | O91: 46189 | P91: greenhouse:graphcore | U91: 46189
A92: =IF($L92="applied","Applied",IF($L92="interview","Interview",IF($L92="offer","Offer",IF($L92="rejected","Rejected",IF($L92="ignore","Ignore",IF($L92="archive","Archive",IF($L92="closed","Closed",IF($B92="","Unscored",IF(AND($B92>=8,OR($H92="",$H92-TODAY()<=14)),"P1 Apply",IF($B92>=7,"P2 Strong",IF($B92>=5,"P3 Maybe","P4 Low"))))))))))) | B92: 5 | C92: Senior/Lead | D92: Automation Engineer | E92: Graphcore | F92: Bristol, UK | I92: =IF($H92="","",$H92-TODAY()) | J92: Open posting | L92: new | N92: 120b4cec280e9d6812295a001d8f41371fe85412 | O92: 46189 | P92: greenhouse:graphcore | U92: 46189
A93: =IF($L93="applied","Applied",IF($L93="interview","Interview",IF($L93="offer","Offer",IF($L93="rejected","Rejected",IF($L93="ignore","Ignore",IF($L93="archive","Archive",IF($L93="closed","Closed",IF($B93="","Unscored",IF(AND($B93>=8,OR($H93="",$H93-TODAY()<=14)),"P1 Apply",IF($B93>=7,"P2 Strong",IF($B93>=5,"P3 Maybe","P4 Low"))))))))))) | B93: 5 | C93: Senior/Lead | D93: BMC Engineer | E93: Graphcore | F93: Gdańsk, Pomeranian Voivodeship, Poland | I93: =IF($H93="","",$H93-TODAY()) | J93: Open posting | L93: new | N93: e43aee60d2c9de02e75b8a67699d6cc0b27a6e3f | O93: 46189 | P93: greenhouse:graphcore | U93: 46189
... A213: =IF($L213="applied","Applied",IF($L213="interview","Interview",IF($L213="offer","Offer",IF($L213="rejected","Rejected",IF($L213="ignore","Ignore",IF($L213="archive","Archive",IF($L213="closed","Closed",IF($B213="","Unscored",IF(AND($B213>=8,OR($H213="",$H213-TODAY()<=14)),"P1 Apply",IF($B213>=7,"P2 Strong",IF($B213>=5,"P3 Maybe","P4 Low"))))))))))) | B213: 5 | C213: Senior/Lead | D213: Vice President, Creative & Integrated Marketing | E213: Cerebras | F213: Sunnyvale, CA | I213: =IF($H213="","",$H213-TODAY()) | J213: Open posting | L213: new | N213: a615c2da3d0bd2f0b20d7a24bd608ed3e32f8e0d | O213: 46175 | P213: greenhouse:cerebrassystems | U213: 46189
A214: =IF($L214="applied","Applied",IF($L214="interview","Interview",IF($L214="offer","Offer",IF($L214="rejected","Rejected",IF($L214="ignore","Ignore",IF($L214="archive","Archive",IF($L214="closed","Closed",IF($B214="","Unscored",IF(AND($B214>=8,OR($H214="",$H214-TODAY()<=14)),"P1 Apply",IF($B214>=7,"P2 Strong",IF($B214>=5,"P3 Maybe","P4 Low"))))))))))) | B214: 5 | C214: Unspecified | D214: NoC Design Verification Engineer | E214: SiFive | F214: Ahmedabad, India | I214: =IF($H214="","",$H214-TODAY()) | J214: Open posting | L214: new | N214: 87907efc409f14f911b2adf9c50e03e5726075ce | P214: workday | U214: 46189
A215: =IF($L215="applied","Applied",IF($L215="interview","Interview",IF($L215="offer","Offer",IF($L215="rejected","Rejected",IF($L215="ignore","Ignore",IF($L215="archive","Archive",IF($L215="closed","Closed",IF($B215="","Unscored",IF(AND($B215>=8,OR($H215="",$H215-TODAY()<=14)),"P1 Apply",IF($B215>=7,"P2 Strong",IF($B215>=5,"P3 Maybe","P4 Low"))))))))))) | B215: 5 | C215: Manager/Owner | D215: Technical Functional Safety Program Manager | E215: SiFive | F215: 3 Locations | I215: =IF($H215="","",$H215-TODAY()) | J215: Open posting | L215: new | N215: e3c1c8382133edf82cfa8ef341a928b40e55f149 | P215: workday | U215: 46189
A216: =IF($L216="applied","Applied",IF($L216="interview","Interview",IF($L216="offer","Offer",IF($L216="rejected","Rejected",IF($L216="ignore","Ignore",IF($L216="archive","Archive",IF($L216="closed","Closed",IF($B216="","Unscored",IF(AND($B216>=8,OR($H216="",$H216-TODAY()<=14)),"P1 Apply",IF($B216>=7,"P2 Strong",IF($B216>=5,"P3 Maybe","P4 Low"))))))))))) | B216: 5 | C216: Unspecified | D216: Sr. CPU DV Engineer | E216: SiFive | F216: Hyderabad, India | I216: =IF($H216="","",$H216-TODAY()) | J216: Open posting | L216: new | N216: 039419eea0449aa76447183c0c21d70bb2a2b66f | P216: workday | U216: 46189
A217: =IF($L217="applied","Applied",IF($L217="interview","Interview",IF($L217="offer","Offer",IF($L217="rejected","Rejected",IF($L217="ignore","Ignore",IF($L217="archive","Archive",IF($L217="closed","Closed",IF($B217="","Unscored",IF(AND($B217>=8,OR($H217="",$H217-TODAY()<=14)),"P1 Apply",IF($B217>=7,"P2 Strong",IF($B217>=5,"P3 Maybe","P4 Low"))))))))))) | B217: 5 | C217: Internship | D217: Intern - Design Verification Infrastructure Engineer - Platform | E217: SiFive | F217: 4 Locations | I217: =IF($H217="","",$H217-TODAY()) | J217: Open posting | L217: new | N217: 32aa78681f55ad034379f76991560cb0cb0f0835 | P217: workday | U217: 46189
A218: =IF($L218="applied","Applied",IF($L218="interview","Interview",IF($L218="offer","Offer",IF($L218="rejected","Rejected",IF($L218="ignore","Ignore",IF($L218="archive","Archive",IF($L218="closed","Closed",IF($B218="","Unscored",IF(AND($B218>=8,OR($H218="",$H218-TODAY()<=14)),"P1 Apply",IF($B218>=7,"P2 Strong",IF($B218>=5,"P3 Maybe","P4 Low"))))))))))) | B218: 5 | C218: Unspecified | D218: RTL Design Engineer | E218: SiFive | F218: Hsinchu, Taiwan | I218: =IF($H218="","",$H218-TODAY()) | J218: Open posting | L218: new | N218: 52e062e12c438d4e9dbc9f593f659bb5776e4225 | P218: workday | U218: 46189
A219: =IF($L219="applied","Applied",IF($L219="interview","Interview",IF($L219="offer","Offer",IF($L219="rejected","Rejected",IF($L219="ignore","Ignore",IF($L219="archive","Archive",IF($L219="closed","Closed",IF($B219="","Unscored",IF(AND($B219>=8,OR($H219="",$H219-TODAY()<=14)),"P1 Apply",IF($B219>=7,"P2 Strong",IF($B219>=5,"P3 Maybe","P4 Low"))))))))))) | B219: 5 | C219: Unspecified | D219: Performance Model Engineer | E219: SiFive | F219: 2 Locations | I219: =IF($H219="","",$H219-TODAY()) | J219: Open posting | L219: new | N219: f8f1eb6e4e6c03dd69bc97b94a56bb206ce7104e | P219: workday | U219: 46189
...

Sheet runs
A1: ID | B1: Started | C1: Finished | D1: Duration (s) | E1: Sources OK | F1: Sources Failed | G1: Jobs Scraped | H1: Jobs New | I1: Jobs Closed | J1: Errors
A2: 46 | B2: 2026-06-29T16:57:36.969985 | D2: 0 | E2: 5 | F2: 0 | G2: 3833 | H2: 152 | I2: 0 | J2: []
A3: 45 | B3: 2026-06-29T12:19:08.582039 | D3: 0 | E3: 5 | F3: 0 | G3: 4029 | H3: 308 | I3: 0 | J3: []
A4: 44 | B4: 2026-06-28T20:22:27.934906 | D4: 0 | E4: 5 | F4: 0 | G4: 3844 | H4: 168 | I4: 0 | J4: []
A5: 43 | B5: 2026-06-28T15:04:19.953690 | D5: 0 | E5: 5 | F5: 0 | G5: 3735 | H5: 104 | I5: 0 | J5: []
A6: 42 | B6: 2026-06-28T10:17:59.891534 | D6: 0 | E6: 5 | F6: 0 | G6: 3248 | H6: 0 | I6: 0 | J6: []
A7: 41 | B7: 2026-06-27T20:27:13.121548 | D7: 0 | E7: 5 | F7: 0 | G7: 4106 | H7: 320 | I7: 0 | J7: []
A8: 40 | B8: 2026-06-27T14:45:35.702722 | D8: 0 | E8: 5 | F8: 0 | G8: 3837 | H8: 189 | I8: 0 | J8: []
A9: 39 | B9: 2026-06-27T09:41:27.016531 | D9: 0 | E9: 5 | F9: 0 | G9: 3648 | H9: 185 | I9: 0 | J9: []
A10: 38 | B10: 2026-06-26T20:49:37.549966 | D10: 0 | E10: 5 | F10: 0 | G10: 3866 | H10: 212 | I10: 0 | J10: []
A11: 37 | B11: 2026-06-26T20:08:19.603896 | D11: 0 | E11: 5 | F11: 0 | G11: 3763 | H11: 2161 | I11: 0 | J11: []
A12: 36 | B12: 2026-06-26T15:29:12.111224 | D12: 0 | E12: 5 | F12: 0 | G12: 823 | H12: 37 | I12: 0 | J12: []
A13: 35 | B13: 2026-06-26T10:22:20.681134 | D13: 0 | E13: 5 | F13: 0 | G13: 854 | H13: 13 | I13: 0 | J13: []
... A31: 17 | B31: 2026-06-20T15:15:13.727639 | D31: 0 | E31: 5 | F31: 0 | G31: 950 | H31: 60 | I31: 0 | J31: []

Sheet profile
A1: Key | B1: Value
A2: name | B2: David Cracknell
A3: domain | B3: engineering
A4: secondary_domains | B4: ["finance", "science"]
A5: location.city | B5: Sheffield
A6: location.lat | B6: 53.38
A7: location.lon | B7: -1.47
A8: search_radius_miles | B8: 60
A9: remote_ok | B9: true
A10: education.highest_qualification | B10: MEng Electronic and Computer Engineering
A11: education.institution | B11: University of Sheffield
A12: education.completion_year | B12: 2026
... A30: filters.rejected_company_cooldown_days | B30: 90

Sheet quota
A1: Date | B1: Operation | C1: Model | D1: Calls | E1: Input Tokens | F1: Cached Tokens | G1: Output Tokens | H1: Est. Cost (GBP)
A2: 2026-06-29 | B2: queries | C2: claude-sonnet-4-6 | D2: 2 | E2: 4188 | F2: 0 | G2: 1203 | H2: 0.0245
A3: 2026-06-29 | B3: rank | D3: 1177 | E3: 0 | F3: 0 | G3: 0 | H3: 0
A4: 2026-06-28 | B4: queries | C4: claude-sonnet-4-6 | D4: 3 | E4: 6282 | F4: 0 | G4: 1818 | H4: 0.0369
A5: 2026-06-28 | B5: rank | D5: 1609 | E5: 0 | F5: 0 | G5: 0 | H5: 0
A6: 2026-06-27 | B6: queries | C6: claude-sonnet-4-6 | D6: 3 | E6: 6282 | F6: 0 | G6: 1778 | H6: 0.0364
A7: 2026-06-27 | B7: rank | D7: 1724 | E7: 0 | F7: 0 | G7: 0 | H7: 0
A8: 2026-06-26 | B8: rank | C8: claude-sonnet-4-6 | D8: 9 | E8: 31423 | F8: 12775 | G8: 3103 | H8: 0.0851
A9: 2026-06-26 | B9: queries | C9: claude-sonnet-4-6 | D9: 4 | E9: 6642 | F9: 0 | G9: 1705 | H9: 0.0364
A10: 2026-06-26 | B10: rank | D10: 1132 | E10: 0 | F10: 0 | G10: 0 | H10: 0
A11: 2026-06-25 | B11: rank | C11: claude-sonnet-4-6 | D11: 9 | E11: 31761 | F11: 10950 | G11: 3043 | H11: 0.0891
A12: 2026-06-25 | B12: queries | C12: claude-sonnet-4-6 | D12: 3 | E12: 3681 | F12: 0 | G12: 794 | H12: 0.0184
A13: 2026-06-24 | B13: rank | C13: claude-sonnet-4-6 | D13: 10 | E13: 34789 | F13: 12775 | G13: 3302 | H13: 0.0965
A14: 2026-06-24 | B14: queries | C14: claude-sonnet-4-6 | D14: 3 | E14: 3681 | F14: 0 | G14: 794 | H14: 0.0184
A15: 2026-06-23 | B15: rank | C15: claude-sonnet-4-6 | D15: 10 | E15: 29842 | F15: 12775 | G15: 2984 | H15: 0.0823
A16: 2026-06-23 | B16: queries | C16: claude-sonnet-4-6 | D16: 3 | E16: 3681 | F16: 0 | G16: 797 | H16: 0.0184
A17: 2026-06-22 | B17: rank | C17: claude-sonnet-4-6 | D17: 15 | E17: 51247 | F17: 18255 | G17: 4967 | H17: 0.1452
A18: 2026-06-22 | B18: queries | C18: claude-sonnet-4-6 | D18: 4 | E18: 4362 | F18: 0 | G18: 991 | H18: 0.0224
A19: 2026-06-21 | B19: rank | C19: claude-sonnet-4-6 | D19: 11 | E19: 35469 | F19: 13144 | G19: 3662 | H19: 0.1027
A20: 2026-06-21 | B20: queries | C20: claude-sonnet-4-6 | D20: 3 | E20: 3135 | F20: 0 | G20: 710 | H20: 0.016
A21: 2026-06-20 | B21: rank | C21: claude-sonnet-4-6 | D21: 17 | E21: 58173 | F21: 23002 | G21: 5580 | H21: 0.1598
A22: 2026-06-20 | B22: queries | C22: claude-sonnet-4-6 | D22: 3 | E22: 3135 | F22: 0 | G22: 730 | H22: 0.0163
... A24: 2026-06-19 | B24: queries | C24: claude-sonnet-4-6 | D24: 3 | E24: 3135 | F24: 0 | G24: 730 | H24: 0.0163
A25: 2026-06-19 | B25: queries | D25: 1 | E25: 0 | F25: 0 | G25: 0 | H25: 0
A26: 2026-06-18 | B26: queries | D26: 8 | E26: 0 | F26: 0 | G26: 0 | H26: 0
A27: 2026-06-18 | B27: rank | D27: 129 | E27: 0 | F27: 0 | G27: 0 | H27: 0
A28: 2026-06-17 | B28: rank | D28: 35 | E28: 0 | F28: 0 | G28: 0 | H28: 0
A29: 2026-06-16 | B29: rank | D29: 70 | E29: 0 | F29: 0 | G29: 0 | H29: 0
